Workbook

Sheet README
B2: Debottlenecking Study (Theory of Constraints): Aluminium Enclosure Production Line
B3: SIMULATED / ILLUSTRATIVE DATA. Not a real plant. Stage parameters are benchmark-informed assumptions; replace with time-study data.
B5: Question | C5: One production module must deliver 10,000 good enclosures a week. Where is the constraint, how much output does it cost, which fixes recover it, and what do they cost?
B6: Line | C6: Blank saw > CNC OP10 rough > CNC OP20 finish > deburr / polish > anodising (48-unit rack batches) > inspection > packing. One module is 10% of the 5-million-unit-a-year line modelled in Project 1.
B7: Two models, one answer | C7: Excel (this workbook) does the rate-based Theory of Constraints analysis: capacity, utilisation, takt, OEE, constraint, scenario output and economics, all as formulas. A SimPy discrete-event simulation (simulate.py, 8 replications per scenario) adds what averages hide: breakdowns, cycle-time variability, queues, WIP and lead time. Simulation outputs are pasted on the SimResults sheet.
B8: Five focusing steps | C8: 1 Identify the constraint (BaseAnalysis). 2 Exploit it: get more from what exists (SMED, TPM, yield at the constraint). 3 Subordinate everything else (drum-buffer-rope release). 4 Elevate it: add capacity only if still needed (third line, 7-day working). 5 Repeat: the constraint moves (Fixes sheet shows the next one).
B9: Sheets | C9: Dashboard > Inputs > BaseAnalysis > Fixes (deterministic scenarios) > SimResults (SimPy output, rope sweep) > Economics (gain vs cost) > Sources.
B10: How to use | C10: Change only BLUE cells (stage parameters, fix parameters, costs, 0/1 scenario flags). Everything except SimResults recalculates. If you change stage parameters, re-run simulate.py and run_experiments.py and repaste SimResults so the simulation matches.
B11: Colour code | C11: Blue = input. Black = formula. Green = link to another sheet. Yellow fill = key assumption.
B12: Cost-benefit logic | C12: Gain = extra sellable good units per week (capped at demand) x 50 weeks x contribution per unit. Contribution = Project 1 ex-works price - net material - assumed variable conversion cost. Costs are illustrative one-time and annual amounts; one-time costs are spread over 3 years. Gains assume the customer will buy the recovered units.
B13: Limitations | C13: Simulated line, not a real one. Lots of 6 units move between stages. Failures are operating-time based. Costs of fixes are assumptions to be replaced by quotes. Weekly gain is demand-capped, so fixes beyond the first are worth little unless demand grows.

Sheet Dashboard
A1: Dashboard: finding and fixing the constraint on an enclosure production line
A2: SIMULATED / ILLUSTRATIVE DATA. Every figure is a formula (deterministic metrics) or a pasted SimPy result (SimResults).
A4: Step 1: where is the constraint?
A5: Constraint stage (base case) | B5: =BaseAnalysis!D19 -> Anodising (rack batch)
A6: Maximum good output per week (theory) | B6: =BaseAnalysis!D20 -> 8932.0856
A7: Output as % of demand | B7: =BaseAnalysis!D22 -> 0.89320856
A8: Simulated base output (good units/wk) | B8: =SimResults!D5 -> 8938
A9: OEE of the constraint stage | B9: =BaseAnalysis!D23 -> 0.84165
A10: Takt time per good unit (seconds) | B10: =BaseAnalysis!D16*60 -> 34.56
A11: Next-most-constrained stage | B11: =BaseAnalysis!D24 -> CNC OP20 finish
A13: Steps 2-3: exploit and subordinate
A14: DBR release: WIP reduction vs push (simulated) | B14: =-Economics!M6 -> 0.92103878
A15: Flow time, push release (hours) | B15: =SimResults!H5 -> 67.36
A16: Flow time, DBR release (hours) | B16: =SimResults!H6 -> 5.32
A17: SMED alone: simulated output (good units/wk) | B17: =Economics!C8 -> 9969.1
A18: SMED alone: net annual benefit (USD, module) | B18: =Economics!K8 -> 159788.36
A20: Steps 4-5: elevate only if needed, then repeat
A21: Best scenario by net annual benefit | B21: =INDEX(Economics!B5:B16,MATCH(1,Economics!Q5:Q16,0)) -> SMED: rack batch 52 to 46 min
A22: Its net annual benefit (USD, module) | B22: =INDEX(Economics!K5:K16,MATCH(1,Economics!Q5:Q16,0)) -> 159788.36
A23: Low-cost package (DBR + SMED): net annual benefit (USD) | B23: =Economics!K12 -> 156169.59
A24: Capex route (DBR + third line): net annual benefit (USD) | B24: =Economics!K15 -> -65124.273
A25: Constraint after low-cost package | B25: =Fixes!X12 -> Anodising (rack batch)
A26: Low-cost package: headroom over demand (theory) | B26: =Fixes!AC12 -> 0.0097140257
A27: Low-cost package: full-line net benefit (USD/yr) | B27: =Economics!R12 -> 1561695.9

Sheet Inputs
A1: Inputs and assumptions (simulated line)
A2: Blue = input. Yellow = key assumption. Stage values are illustrative, benchmark-informed (see Sources).
A4: Global parameters
A5: Planned production hours per week | B5: 96 | C5: h/week | K5: 2 shifts x 8 h x 6 days
A6: Planned production minutes per week | B6: =B5*60 -> 5760 | C6: min/week | K6: Formula
A7: Weekly customer demand (good units) | B7: 10000 | C7: units/week | K7: Module target: 10% of Project 1's 5M units a year
A8: Production weeks per year | B8: 50 | C8: weeks | K8: Assumption
A9: Anodising rack size | B9: 48 | C9: units | K9: Assumption: units per rack batch
A10: Ex-works price per unit | B10: 4.161 | C10: USD | K10: From Project 1 model: India base case, before ECMS incentive
A11: Net material cost per unit | B11: 0.203 | C11: USD | K11: From Project 1 model: India base case, net of chip-scrap credit
A12: Variable conversion cost per unit | B12: 0.6 | C12: USD | K12: Assumption: consumables, chemicals, energy that vary with output
A13: Contribution per extra good unit | B13: =B10-B11-B12 -> 3.358 | C13: USD | K13: Formula: price - material - variable conversion
A14: Amortisation period for one-time costs | B14: 3 | C14: years | K14: Assumption
A15: Scale factor, module to full 5M-unit line | B15: 10 | C15: x | K15: Assumption: ten identical modules
A17: Stage parameters
A18: # | B18: Stage | C18: Type | D18: Machines / lines | E18: Ideal cycle per unit (min) | F18: Rack batch time (min) | G18: Availability | H18: Performance | I18: Yield | J18: MTTR (min) | K18: Basis
A19: 1 | B19: Blank saw | C19: Per unit | D19: 1 | E19: 0.3 | G19: 0.92 | H19: 0.95 | I19: 0.995 | J19: 20 | K19: Fast, one saw; not a constraint
A20: 2 | B20: CNC OP10 rough | C20: Per unit | D20: 7 | E20: 2.6 | G20: 0.9 | H20: 0.92 | I20: 0.99 | J20: 25 | K20: Rough milling, 7 machines
A21: 3 | B21: CNC OP20 finish | C21: Per unit | D21: 9 | E21: 3.4 | G21: 0.9 | H21: 0.92 | I21: 0.975 | J21: 25 | K21: Finish milling, 9 machines; availability 90% = world-class threshold [W1]
A22: 4 | B22: Deburr / polish | C22: Per unit | D22: 5 | E22: 1.8 | G22: 0.95 | H22: 0.9 | I22: 0.99 | J22: 15 | K22: Semi-automatic deburr / polish stations
A23: 5 | B23: Anodising (rack batch) | C23: Batch | D23: 2 | E23: =F23/$B$9 -> 1.0833333 | F23: 52 | G23: 0.93 | H23: 1 | I23: 0.905 | J23: 40 | K23: Batch process: 2 rack lines, 52 min per 48-unit rack incl. load, pretreat, anodise, dye, seal
A24: 6 | B24: Inspection | C24: Per unit | D24: 2 | E24: 0.85 | G24: 0.96 | H24: 0.95 | I24: 0.999 | J24: 10 | K24: 100% visual plus sampled CMM
A25: 7 | B25: Packing | C25: Per unit | D25: 2 | E25: 0.5 | G25: 0.97 | H25: 0.95 | I25: 0.999 | J25: 10 | K25: Pack and label
A27: Fix parameters and illustrative costs (all cost values are assumptions)
A28: Code | B28: Fix | C28: Parameter | D28: Unit | E28: One-time cost (USD) | F28: Annual cost (USD) | K28: What it does (TOC step)
A29: DBR | B29: Drum-buffer-rope release | C29: 400 | D29: units ahead of constraint | E29: 10000 | F29: 0 | K29: Subordinate: release only when the buffer ahead of anodising is below the rope; cuts WIP and lead time. Rope 400 units at base capacity, re-sized to 900 after the constraint is sped up
A30: YIELD | B30: Anodising yield improvement | C30: 0.935 | D30: anodising yield | E30: 20000 | F30: 60000 | K30: Exploit: scrap at the constraint wastes constraint hours; better chemistry and process control
A31: SMED | B31: SMED on rack load / unload | C31: 46 | D31: min per rack batch | E31: 40000 | F31: 0 | K31: Exploit: faster rack changeover raises constraint capacity at low cost
A32: SEVEN | B32: Anodising 7 days a week | C32: =7/6 -> 1.1666667 | D32: capacity multiplier | E32: 0 | F32: 120000 | K32: Elevate: extra constraint hours via weekend working
A33: LINE3 | B33: Add third anodising line | C33: 3 | D33: anodising lines | E33: 450000 | F33: 90000 | K33: Elevate: parallel station, capex
A34: TPM | B34: TPM at anodising | C34: 0.96 | D34: anodising availability | E34: 10000 | F34: 35000 | K34: Exploit: preventive maintenance cuts breakdown time at the constraint

Sheet BaseAnalysis
A1: Step 1: identify the constraint (rate-based analysis at target demand)
A2: Capacity = machines x planned minutes x availability x performance / ideal cycle. Utilisation above 100% means the stage cannot keep up with demand.
A4: # | B4: Stage | C4: Machines / lines | D4: Cumulative yield before stage | E4: Load at target (units/wk) | F4: Capacity (units/wk) | G4: Utilisation at target | H4: Effective cycle per unit (min) | I4: Stage takt (min/unit) | J4: OEE | K4: Starts capacity (starts/wk) | L4: Constraint? | M4: Util. rank
A5: =Inputs!A19 -> 1 | B5: =Inputs!B19 -> Blank saw | C5: =Inputs!D19 -> 1 | D5: 1 | E5: =$D$15*D5 -> 11644.541 | F5: =C5*Inputs!$B$6*Inputs!G19*Inputs!H19/Inputs!E19 -> 16780.8 | G5: =E5/F5 -> 0.69392047 | H5: =Inputs!E19/(C5*Inputs!G19*Inputs!H19) -> 0.34324943 | I5: =Inputs!$B$6/E5 -> 0.4946524 | J5: =Inputs!G19*Inputs!H19*Inputs!I19 -> 0.86963 | K5: =F5/D5 -> 16780.8 | L5: =IF(K5=MIN($K$5:$K$11),"CONSTRAINT","") | M5: =RANK(G5,$G$5:$G$11,0) -> 6
A6: =Inputs!A20 -> 2 | B6: =Inputs!B20 -> CNC OP10 rough | C6: =Inputs!D20 -> 7 | D6: =D5*Inputs!I19 -> 0.995 | E6: =$D$15*D6 -> 11586.318 | F6: =C6*Inputs!$B$6*Inputs!G20*Inputs!H20/Inputs!E20 -> 12840.369 | G6: =E6/F6 -> 0.90233526 | H6: =Inputs!E20/(C6*Inputs!G20*Inputs!H20) -> 0.44858523 | I6: =Inputs!$B$6/E6 -> 0.4971381 | J6: =Inputs!G20*Inputs!H20*Inputs!I20 -> 0.81972 | K6: =F6/D6 -> 12904.894 | L6: =IF(K6=MIN($K$5:$K$11),"CONSTRAINT","") | M6: =RANK(G6,$G$5:$G$11,0) -> 3
A7: =Inputs!A21 -> 3 | B7: =Inputs!B21 -> CNC OP20 finish | C7: =Inputs!D21 -> 9 | D7: =D6*Inputs!I20 -> 0.98505 | E7: =$D$15*D7 -> 11470.455 | F7: =C7*Inputs!$B$6*Inputs!G21*Inputs!H21/Inputs!E21 -> 12624.565 | G7: =E7/F7 -> 0.90858219 | H7: =Inputs!E21/(C7*Inputs!G21*Inputs!H21) -> 0.45625335 | I7: =Inputs!$B$6/E7 -> 0.50215969 | J7: =Inputs!G21*Inputs!H21*Inputs!I21 -> 0.8073 | K7: =F7/D7 -> 12816.166 | L7: =IF(K7=MIN($K$5:$K$11),"CONSTRAINT","") | M7: =RANK(G7,$G$5:$G$11,0) -> 2
A8: =Inputs!A22 -> 4 | B8: =Inputs!B22 -> Deburr / polish | C8: =Inputs!D22 -> 5 | D8: =D7*Inputs!I21 -> 0.96042375 | E8: =$D$15*D8 -> 11183.693 | F8: =C8*Inputs!$B$6*Inputs!G22*Inputs!H22/Inputs!E22 -> 13680 | G8: =E8/F8 -> 0.81752144 | H8: =Inputs!E22/(C8*Inputs!G22*Inputs!H22) -> 0.42105263 | I8: =Inputs!$B$6/E8 -> 0.51503558 | J8: =Inputs!G22*Inputs!H22*Inputs!I22 -> 0.84645 | K8: =F8/D8 -> 14243.713 | L8: =IF(K8=MIN($K$5:$K$11),"CONSTRAINT","") | M8: =RANK(G8,$G$5:$G$11,0) -> 4
A9: =Inputs!A23 -> 5 | B9: =Inputs!B23 -> Anodising (rack batch) | C9: =Inputs!D23 -> 2 | D9: =D8*Inputs!I22 -> 0.95081951 | E9: =$D$15*D9 -> 11071.856 | F9: =C9*Inputs!$B$6*Inputs!G23*Inputs!H23/Inputs!E23 -> 9889.4769 | G9: =E9/F9 -> 1.1195594 | H9: =Inputs!E23/(C9*Inputs!G23*Inputs!H23) -> 0.58243728 | I9: =Inputs!$B$6/E9 -> 0.52023796 | J9: =Inputs!G23*Inputs!H23*Inputs!I23 -> 0.84165 | K9: =F9/D9 -> 10401.003 | L9: =IF(K9=MIN($K$5:$K$11),"CONSTRAINT","") -> CONSTRAINT | M9: =RANK(G9,$G$5:$G$11,0) -> 1
A10: =Inputs!A24 -> 6 | B10: =Inputs!B24 -> Inspection | C10: =Inputs!D24 -> 2 | D10: =D9*Inputs!I23 -> 0.86049166 | E10: =$D$15*D10 -> 10020.03 | F10: =C10*Inputs!$B$6*Inputs!G24*Inputs!H24/Inputs!E24 -> 12360.282 | G10: =E10/F10 -> 0.81066352 | H10: =Inputs!E24/(C10*Inputs!G24*Inputs!H24) -> 0.46600877 | I10: =Inputs!$B$6/E10 -> 0.57484858 | J10: =Inputs!G24*Inputs!H24*Inputs!I24 -> 0.911088 | K10: =F10/D10 -> 14364.209 | L10: =IF(K10=MIN($K$5:$K$11),"CONSTRAINT","") | M10: =RANK(G10,$G$5:$G$11,0) -> 5
A11: =Inputs!A25 -> 7 | B11: =Inputs!B25 -> Packing | C11: =Inputs!D25 -> 2 | D11: =D10*Inputs!I24 -> 0.85963117 | E11: =$D$15*D11 -> 10010.01 | F11: =C11*Inputs!$B$6*Inputs!G25*Inputs!H25/Inputs!E25 -> 21231.36 | G11: =E11/F11 -> 0.47147286 | H11: =Inputs!E25/(C11*Inputs!G25*Inputs!H25) -> 0.2712968 | I11: =Inputs!$B$6/E11 -> 0.575424 | J11: =Inputs!G25*Inputs!H25*Inputs!I25 -> 0.9205785 | K11: =F11/D11 -> 24698.22 | L11: =IF(K11=MIN($K$5:$K$11),"CONSTRAINT","") | M11: =RANK(G11,$G$5:$G$11,0) -> 7
A13: Line summary
A14: Total line yield (first-pass) | D14: =PRODUCT(Inputs!I19:I25) -> 0.85877154
A15: Starts per week needed to meet demand | D15: =Inputs!B7/D14 -> 11644.541
A16: Takt time per good unit (min) | D16: =Inputs!B6/Inputs!B7 -> 0.576
A17: Takt time per start (min) | D17: =Inputs!B6/D15 -> 0.4946524
A18: Maximum starts per week the line can support | D18: =MIN(K5:K11) -> 10401.003
A19: Constraint stage | D19: =INDEX(B5:B11,MATCH(D18,K5:K11,0)) -> Anodising (rack batch)
A20: Maximum good output per week | D20: =D18*D14 -> 8932.0856
A21: Shortfall versus demand (units/wk) | D21: =D20-Inputs!B7 -> -1067.9144
A22: Output as % of demand | D22: =D20/Inputs!B7 -> 0.89320856
A23: OEE of the constraint stage | D23: =INDEX(J5:J11,MATCH(D18,K5:K11,0)) -> 0.84165
A24: Next-most-constrained stage | D24: =INDEX(B5:B11,MATCH(SMALL(K5:K11,2),K5:K11,0)) -> CNC OP20 finish
A25: Next stage: utilisation at target | D25: =INDEX(G5:G11,MATCH(SMALL(K5:K11,2),K5:K11,0)) -> 0.90858219
A27: TOC rule: an hour lost at the constraint is an hour lost for the whole line; an hour saved at a non-constraint is a mirage.

Sheet Fixes
A1: Steps 2-5: deterministic scenario analysis (theoretical output, no variability)
A2: Set 1/0 flags to switch fixes on. Levers, capacities, constraint and output recalculate. The constraint moves after each fix (step 5).
A4: ID | B4: Scenario | C4: DBR | D4: YIELD | E4: SMED | F4: SEVEN | G4: LINE3 | H4: TPM | I4: Anodising lines | J4: Rack batch (min) | K4: Anodising availability | L4: Time multiplier | M4: Anodising yield | N4: Anodising capacity (units/wk) | O4: Line yield | P4: =BaseAnalysis!B5 -> Blank saw | Q4: =BaseAnalysis!B6 -> CNC OP10 rough | R4: =BaseAnalysis!B7 -> CNC OP20 finish | S4: =BaseAnalysis!B8 -> Deburr / polish | T4: =BaseAnalysis!B9 -> Anodising (rack batch) | U4: =BaseAnalysis!B10 -> Inspection | V4: =BaseAnalysis!B11 -> Packing | W4: Max starts (starts/wk) | X4: Constraint after fix | Y4: Max good output (units/wk) | Z4: Sellable (capped at demand) | AA4: Gain vs base (units/wk) | AB4: Starts needed for demand | AC4: Headroom over demand | AD4: One-time cost (USD) | AE4: Annual cost (USD)
A5: C0 | B5: Base case (push release) | C5: 0 | D5: 0 | E5: 0 | F5: 0 | G5: 0 | H5: 0 | I5: =IF(G5=1,Inputs!$C$33,Inputs!$D$23) -> 2 | J5: =IF(E5=1,Inputs!$C$31,Inputs!$F$23) -> 52 | K5: =IF(H5=1,Inputs!$C$34,Inputs!$G$23) -> 0.93 | L5: =IF(F5=1,Inputs!$C$32,1) -> 1 | M5: =IF(D5=1,Inputs!$C$30,Inputs!$I$23) -> 0.905 | N5: =I5*Inputs!$B$6*L5*K5*Inputs!$H$23/(J5/Inputs!$B$9) -> 9889.4769 | O5: =Inputs!$I$19*Inputs!$I$20*Inputs!$I$21*Inputs!$I$22*M5*Inputs!$I$24*Inputs!$I$25 -> 0.85877154 | P5: =BaseAnalysis!$K$5 -> 16780.8 | Q5: =BaseAnalysis!$K$6 -> 12904.894 | R5: =BaseAnalysis!$K$7 -> 12816.166 | S5: =BaseAnalysis!$K$8 -> 14243.713 | T5: =N5/BaseAnalysis!$D$9 -> 10401.003 | U5: =BaseAnalysis!$F$10/(BaseAnalysis!$D$9*M5) -> 14364.209 | V5: =BaseAnalysis!$F$11/(BaseAnalysis!$D$9*M5*Inputs!$I$24) -> 24698.22 | W5: =MIN(P5:V5) -> 10401.003 | X5: =INDEX($P$4:$V$4,MATCH(W5,P5:V5,0)) -> Anodising (rack batch) | Y5: =W5*O5 -> 8932.0856 | Z5: =MIN(Y5,Inputs!$B$7) -> 8932.0856 | AA5: =Z5-$Z$5 -> 0 | AB5: =Inputs!$B$7/O5 -> 11644.541 | AC5: =Y5/Inputs!$B$7-1 -> -0.10679144 | AD5: =C5*Inputs!$E$29+D5*Inputs!$E$30+E5*Inputs!$E$31+F5*Inputs!$E$32+G5*Inputs!$E$33+H5*Inputs!$E$34 -> 0 | AE5: =C5*Inputs!$F$29+D5*Inputs!$F$30+E5*Inputs!$F$31+F5*Inputs!$F$32+G5*Inputs!$F$33+H5*Inputs!$F$34 -> 0
A6: C1 | B6: DBR release only | C6: 1 | D6: 0 | E6: 0 | F6: 0 | G6: 0 | H6: 0 | I6: =IF(G6=1,Inputs!$C$33,Inputs!$D$23) -> 2 | J6: =IF(E6=1,Inputs!$C$31,Inputs!$F$23) -> 52 | K6: =IF(H6=1,Inputs!$C$34,Inputs!$G$23) -> 0.93 | L6: =IF(F6=1,Inputs!$C$32,1) -> 1 | M6: =IF(D6=1,Inputs!$C$30,Inputs!$I$23) -> 0.905 | N6: =I6*Inputs!$B$6*L6*K6*Inputs!$H$23/(J6/Inputs!$B$9) -> 9889.4769 | O6: =Inputs!$I$19*Inputs!$I$20*Inputs!$I$21*Inputs!$I$22*M6*Inputs!$I$24*Inputs!$I$25 -> 0.85877154 | P6: =BaseAnalysis!$K$5 -> 16780.8 | Q6: =BaseAnalysis!$K$6 -> 12904.894 | R6: =BaseAnalysis!$K$7 -> 12816.166 | S6: =BaseAnalysis!$K$8 -> 14243.713 | T6: =N6/BaseAnalysis!$D$9 -> 10401.003 | U6: =BaseAnalysis!$F$10/(BaseAnalysis!$D$9*M6) -> 14364.209 | V6: =BaseAnalysis!$F$11/(BaseAnalysis!$D$9*M6*Inputs!$I$24) -> 24698.22 | W6: =MIN(P6:V6) -> 10401.003 | X6: =INDEX($P$4:$V$4,MATCH(W6,P6:V6,0)) -> Anodising (rack batch) | Y6: =W6*O6 -> 8932.0856 | Z6: =MIN(Y6,Inputs!$B$7) -> 8932.0856 | AA6: =Z6-$Z$5 -> 0 | AB6: =Inputs!$B$7/O6 -> 11644.541 | AC6: =Y6/Inputs!$B$7-1 -> -0.10679144 | AD6: =C6*Inputs!$E$29+D6*Inputs!$E$30+E6*Inputs!$E$31+F6*Inputs!$E$32+G6*Inputs!$E$33+H6*Inputs!$E$34 -> 10000 | AE6: =C6*Inputs!$F$29+D6*Inputs!$F$30+E6*Inputs!$F$31+F6*Inputs!$F$32+G6*Inputs!$F$33+H6*Inputs!$F$34 -> 0
A7: C2 | B7: Anodising yield 90.5% to 93.5% | C7: 0 | D7: 1 | E7: 0 | F7: 0 | G7: 0 | H7: 0 | I7: =IF(G7=1,Inputs!$C$33,Inputs!$D$23) -> 2 | J7: =IF(E7=1,Inputs!$C$31,Inputs!$F$23) -> 52 | K7: =IF(H7=1,Inputs!$C$34,Inputs!$G$23) -> 0.93 | L7: =IF(F7=1,Inputs!$C$32,1) -> 1 | M7: =IF(D7=1,Inputs!$C$30,Inputs!$I$23) -> 0.935 | N7: =I7*Inputs!$B$6*L7*K7*Inputs!$H$23/(J7/Inputs!$B$9) -> 9889.4769 | O7: =Inputs!$I$19*Inputs!$I$20*Inputs!$I$21*Inputs!$I$22*M7*Inputs!$I$24*Inputs!$I$25 -> 0.8872391 | P7: =BaseAnalysis!$K$5 -> 16780.8 | Q7: =BaseAnalysis!$K$6 -> 12904.894 | R7: =BaseAnalysis!$K$7 -> 12816.166 | S7: =BaseAnalysis!$K$8 -> 14243.713 | T7: =N7/BaseAnalysis!$D$9 -> 10401.003 | U7: =BaseAnalysis!$F$10/(BaseAnalysis!$D$9*M7) -> 13903.326 | V7: =BaseAnalysis!$F$11/(BaseAnalysis!$D$9*M7*Inputs!$I$24) -> 23905.764 | W7: =MIN(P7:V7) -> 10401.003 | X7: =INDEX($P$4:$V$4,MATCH(W7,P7:V7,0)) -> Anodising (rack batch) | Y7: =W7*O7 -> 9228.1768 | Z7: =MIN(Y7,Inputs!$B$7) -> 9228.1768 | AA7: =Z7-$Z$5 -> 296.09124 | AB7: =Inputs!$B$7/O7 -> 11270.919 | AC7: =Y7/Inputs!$B$7-1 -> -0.077182315 | AD7: =C7*Inputs!$E$29+D7*Inputs!$E$30+E7*Inputs!$E$31+F7*Inputs!$E$32+G7*Inputs!$E$33+H7*Inputs!$E$34 -> 20000 | AE7: =C7*Inputs!$F$29+D7*Inputs!$F$30+E7*Inputs!$F$31+F7*Inputs!$F$32+G7*Inputs!$F$33+H7*Inputs!$F$34 -> 60000
A8: C3 | B8: SMED: rack batch 52 to 46 min | C8: 0 | D8: 0 | E8: 1 | F8: 0 | G8: 0 | H8: 0 | I8: =IF(G8=1,Inputs!$C$33,Inputs!$D$23) -> 2 | J8: =IF(E8=1,Inputs!$C$31,Inputs!$F$23) -> 46 | K8: =IF(H8=1,Inputs!$C$34,Inputs!$G$23) -> 0.93 | L8: =IF(F8=1,Inputs!$C$32,1) -> 1 | M8: =IF(D8=1,Inputs!$C$30,Inputs!$I$23) -> 0.905 | N8: =I8*Inputs!$B$6*L8*K8*Inputs!$H$23/(J8/Inputs!$B$9) -> 11179.409 | O8: =Inputs!$I$19*Inputs!$I$20*Inputs!$I$21*Inputs!$I$22*M8*Inputs!$I$24*Inputs!$I$25 -> 0.85877154 | P8: =BaseAnalysis!$K$5 -> 16780.8 | Q8: =BaseAnalysis!$K$6 -> 12904.894 | R8: =BaseAnalysis!$K$7 -> 12816.166 | S8: =BaseAnalysis!$K$8 -> 14243.713 | T8: =N8/BaseAnalysis!$D$9 -> 11757.656 | U8: =BaseAnalysis!$F$10/(BaseAnalysis!$D$9*M8) -> 14364.209 | V8: =BaseAnalysis!$F$11/(BaseAnalysis!$D$9*M8*Inputs!$I$24) -> 24698.22 | W8: =MIN(P8:V8) -> 11757.656 | X8: =INDEX($P$4:$V$4,MATCH(W8,P8:V8,0)) -> Anodising (rack batch) | Y8: =W8*O8 -> 10097.14 | Z8: =MIN(Y8,Inputs!$B$7) -> 10000 | AA8: =Z8-$Z$5 -> 1067.9144 | AB8: =Inputs!$B$7/O8 -> 11644.541 | AC8: =Y8/Inputs!$B$7-1 -> 0.0097140257 | AD8: =C8*Inputs!$E$29+D8*Inputs!$E$30+E8*Inputs!$E$31+F8*Inputs!$E$32+G8*Inputs!$E$33+H8*Inputs!$E$34 -> 40000 | AE8: =C8*Inputs!$F$29+D8*Inputs!$F$30+E8*Inputs!$F$31+F8*Inputs!$F$32+G8*Inputs!$F$33+H8*Inputs!$F$34 -> 0
A9: C4 | B9: Anodising 7 days a week | C9: 0 | D9: 0 | E9: 0 | F9: 1 | G9: 0 | H9: 0 | I9: =IF(G9=1,Inputs!$C$33,Inputs!$D$23) -> 2 | J9: =IF(E9=1,Inputs!$C$31,Inputs!$F$23) -> 52 | K9: =IF(H9=1,Inputs!$C$34,Inputs!$G$23) -> 0.93 | L9: =IF(F9=1,Inputs!$C$32,1) -> 1.1666667 | M9: =IF(D9=1,Inputs!$C$30,Inputs!$I$23) -> 0.905 | N9: =I9*Inputs!$B$6*L9*K9*Inputs!$H$23/(J9/Inputs!$B$9) -> 11537.723 | O9: =Inputs!$I$19*Inputs!$I$20*Inputs!$I$21*Inputs!$I$22*M9*Inputs!$I$24*Inputs!$I$25 -> 0.85877154 | P9: =BaseAnalysis!$K$5 -> 16780.8 | Q9: =BaseAnalysis!$K$6 -> 12904.894 | R9: =BaseAnalysis!$K$7 -> 12816.166 | S9: =BaseAnalysis!$K$8 -> 14243.713 | T9: =N9/BaseAnalysis!$D$9 -> 12134.504 | U9: =BaseAnalysis!$F$10/(BaseAnalysis!$D$9*M9) -> 14364.209 | V9: =BaseAnalysis!$F$11/(BaseAnalysis!$D$9*M9*Inputs!$I$24) -> 24698.22 | W9: =MIN(P9:V9) -> 12134.504 | X9: =INDEX($P$4:$V$4,MATCH(W9,P9:V9,0)) -> Anodising (rack batch) | Y9: =W9*O9 -> 10420.767 | Z9: =MIN(Y9,Inputs!$B$7) -> 10000 | AA9: =Z9-$Z$5 -> 1067.9144 | AB9: =Inputs!$B$7/O9 -> 11644.541 | AC9: =Y9/Inputs!$B$7-1 -> 0.042076655 | AD9: =C9*Inputs!$E$29+D9*Inputs!$E$30+E9*Inputs!$E$31+F9*Inputs!$E$32+G9*Inputs!$E$33+H9*Inputs!$E$34 -> 0 | AE9: =C9*Inputs!$F$29+D9*Inputs!$F$30+E9*Inputs!$F$31+F9*Inputs!$F$32+G9*Inputs!$F$33+H9*Inputs!$F$34 -> 120000
A10: C5 | B10: Add third anodising line | C10: 0 | D10: 0 | E10: 0 | F10: 0 | G10: 1 | H10: 0 | I10: =IF(G10=1,Inputs!$C$33,Inputs!$D$23) -> 3 | J10: =IF(E10=1,Inputs!$C$31,Inputs!$F$23) -> 52 | K10: =IF(H10=1,Inputs!$C$34,Inputs!$G$23) -> 0.93 | L10: =IF(F10=1,Inputs!$C$32,1) -> 1 | M10: =IF(D10=1,Inputs!$C$30,Inputs!$I$23) -> 0.905 | N10: =I10*Inputs!$B$6*L10*K10*Inputs!$H$23/(J10/Inputs!$B$9) -> 14834.215 | O10: =Inputs!$I$19*Inputs!$I$20*Inputs!$I$21*Inputs!$I$22*M10*Inputs!$I$24*Inputs!$I$25 -> 0.85877154 | P10: =BaseAnalysis!$K$5 -> 16780.8 | Q10: =BaseAnalysis!$K$6 -> 12904.894 | R10: =BaseAnalysis!$K$7 -> 12816.166 | S10: =BaseAnalysis!$K$8 -> 14243.713 | T10: =N10/BaseAnalysis!$D$9 -> 15601.505 | U10: =BaseAnalysis!$F$10/(BaseAnalysis!$D$9*M10) -> 14364.209 | V10: =BaseAnalysis!$F$11/(BaseAnalysis!$D$9*M10*Inputs!$I$24) -> 24698.22 | W10: =MIN(P10:V10) -> 12816.166 | X10: =INDEX($P$4:$V$4,MATCH(W10,P10:V10,0)) -> CNC OP20 finish | Y10: =W10*O10 -> 11006.159 | Z10: =MIN(Y10,Inputs!$B$7) -> 10000 | AA10: =Z10-$Z$5 -> 1067.9144 | AB10: =Inputs!$B$7/O10 -> 11644.541 | AC10: =Y10/Inputs!$B$7-1 -> 0.10061589 | AD10: =C10*Inputs!$E$29+D10*Inputs!$E$30+E10*Inputs!$E$31+F10*Inputs!$E$32+G10*Inputs!$E$33+H10*Inputs!$E$34 -> 450000 | AE10: =C10*Inputs!$F$29+D10*Inputs!$F$30+E10*Inputs!$F$31+F10*Inputs!$F$32+G10*Inputs!$F$33+H10*Inputs!$F$34 -> 90000
A11: C6 | B11: TPM: anodising availability 96% | C11: 0 | D11: 0 | E11: 0 | F11: 0 | G11: 0 | H11: 1 | I11: =IF(G11=1,Inputs!$C$33,Inputs!$D$23) -> 2 | J11: =IF(E11=1,Inputs!$C$31,Inputs!$F$23) -> 52 | K11: =IF(H11=1,Inputs!$C$34,Inputs!$G$23) -> 0.96 | L11: =IF(F11=1,Inputs!$C$32,1) -> 1 | M11: =IF(D11=1,Inputs!$C$30,Inputs!$I$23) -> 0.905 | N11: =I11*Inputs!$B$6*L11*K11*Inputs!$H$23/(J11/Inputs!$B$9) -> 10208.492 | O11: =Inputs!$I$19*Inputs!$I$20*Inputs!$I$21*Inputs!$I$22*M11*Inputs!$I$24*Inputs!$I$25 -> 0.85877154 | P11: =BaseAnalysis!$K$5 -> 16780.8 | Q11: =BaseAnalysis!$K$6 -> 12904.894 | R11: =BaseAnalysis!$K$7 -> 12816.166 | S11: =BaseAnalysis!$K$8 -> 14243.713 | T11: =N11/BaseAnalysis!$D$9 -> 10736.52 | U11: =BaseAnalysis!$F$10/(BaseAnalysis!$D$9*M11) -> 14364.209 | V11: =BaseAnalysis!$F$11/(BaseAnalysis!$D$9*M11*Inputs!$I$24) -> 24698.22 | W11: =MIN(P11:V11) -> 10736.52 | X11: =INDEX($P$4:$V$4,MATCH(W11,P11:V11,0)) -> Anodising (rack batch) | Y11: =W11*O11 -> 9220.2174 | Z11: =MIN(Y11,Inputs!$B$7) -> 9220.2174 | AA11: =Z11-$Z$5 -> 288.13179 | AB11: =Inputs!$B$7/O11 -> 11644.541 | AC11: =Y11/Inputs!$B$7-1 -> -0.077978259 | AD11: =C11*Inputs!$E$29+D11*Inputs!$E$30+E11*Inputs!$E$31+F11*Inputs!$E$32+G11*Inputs!$E$33+H11*Inputs!$E$34 -> 10000 | AE11: =C11*Inputs!$F$29+D11*Inputs!$F$30+E11*Inputs!$F$31+F11*Inputs!$F$32+G11*Inputs!$F$33+H11*Inputs!$F$34 -> 35000
A12: C7 | B12: Low-cost package: DBR + SMED | C12: 1 | D12: 0 | E12: 1 | F12: 0 | G12: 0 | H12: 0 | I12: =IF(G12=1,Inputs!$C$33,Inputs!$D$23) -> 2 | J12: =IF(E12=1,Inputs!$C$31,Inputs!$F$23) -> 46 | K12: =IF(H12=1,Inputs!$C$34,Inputs!$G$23) -> 0.93 | L12: =IF(F12=1,Inputs!$C$32,1) -> 1 | M12: =IF(D12=1,Inputs!$C$30,Inputs!$I$23) -> 0.905 | N12: =I12*Inputs!$B$6*L12*K12*Inputs!$H$23/(J12/Inputs!$B$9) -> 11179.409 | O12: =Inputs!$I$19*Inputs!$I$20*Inputs!$I$21*Inputs!$I$22*M12*Inputs!$I$24*Inputs!$I$25 -> 0.85877154 | P12: =BaseAnalysis!$K$5 -> 16780.8 | Q12: =BaseAnalysis!$K$6 -> 12904.894 | R12: =BaseAnalysis!$K$7 -> 12816.166 | S12: =BaseAnalysis!$K$8 -> 14243.713 | T12: =N12/BaseAnalysis!$D$9 -> 11757.656 | U12: =BaseAnalysis!$F$10/(BaseAnalysis!$D$9*M12) -> 14364.209 | V12: =BaseAnalysis!$F$11/(BaseAnalysis!$D$9*M12*Inputs!$I$24) -> 24698.22 | W12: =MIN(P12:V12) -> 11757.656 | X12: =INDEX($P$4:$V$4,MATCH(W12,P12:V12,0)) -> Anodising (rack batch) | Y12: =W12*O12 -> 10097.14 | Z12: =MIN(Y12,Inputs!$B$7) -> 10000 | AA12: =Z12-$Z$5 -> 1067.9144 | AB12: =Inputs!$B$7/O12 -> 11644.541 | AC12: =Y12/Inputs!$B$7-1 -> 0.0097140257 | AD12: =C12*Inputs!$E$29+D12*Inputs!$E$30+E12*Inputs!$E$31+F12*Inputs!$E$32+G12*Inputs!$E$33+H12*Inputs!$E$34 -> 50000 | AE12: =C12*Inputs!$F$29+D12*Inputs!$F$30+E12*Inputs!$F$31+F12*Inputs!$F$32+G12*Inputs!$F$33+H12*Inputs!$F$34 -> 0
A13: C8 | B13: DBR + SMED + yield at constraint | C13: 1 | D13: 1 | E13: 1 | F13: 0 | G13: 0 | H13: 0 | I13: =IF(G13=1,Inputs!$C$33,Inputs!$D$23) -> 2 | J13: =IF(E13=1,Inputs!$C$31,Inputs!$F$23) -> 46 | K13: =IF(H13=1,Inputs!$C$34,Inputs!$G$23) -> 0.93 | L13: =IF(F13=1,Inputs!$C$32,1) -> 1 | M13: =IF(D13=1,Inputs!$C$30,Inputs!$I$23) -> 0.935 | N13: =I13*Inputs!$B$6*L13*K13*Inputs!$H$23/(J13/Inputs!$B$9) -> 11179.409 | O13: =Inputs!$I$19*Inputs!$I$20*Inputs!$I$21*Inputs!$I$22*M13*Inputs!$I$24*Inputs!$I$25 -> 0.8872391 | P13: =BaseAnalysis!$K$5 -> 16780.8 | Q13: =BaseAnalysis!$K$6 -> 12904.894 | R13: =BaseAnalysis!$K$7 -> 12816.166 | S13: =BaseAnalysis!$K$8 -> 14243.713 | T13: =N13/BaseAnalysis!$D$9 -> 11757.656 | U13: =BaseAnalysis!$F$10/(BaseAnalysis!$D$9*M13) -> 13903.326 | V13: =BaseAnalysis!$F$11/(BaseAnalysis!$D$9*M13*Inputs!$I$24) -> 23905.764 | W13: =MIN(P13:V13) -> 11757.656 | X13: =INDEX($P$4:$V$4,MATCH(W13,P13:V13,0)) -> Anodising (rack batch) | Y13: =W13*O13 -> 10431.852 | Z13: =MIN(Y13,Inputs!$B$7) -> 10000 | AA13: =Z13-$Z$5 -> 1067.9144 | AB13: =Inputs!$B$7/O13 -> 11270.919 | AC13: =Y13/Inputs!$B$7-1 -> 0.043185209 | AD13: =C13*Inputs!$E$29+D13*Inputs!$E$30+E13*Inputs!$E$31+F13*Inputs!$E$32+G13*Inputs!$E$33+H13*Inputs!$E$34 -> 70000 | AE13: =C13*Inputs!$F$29+D13*Inputs!$F$30+E13*Inputs!$F$31+F13*Inputs!$F$32+G13*Inputs!$F$33+H13*Inputs!$F$34 -> 60000
A14: C9 | B14: DBR + SMED + TPM | C14: 1 | D14: 0 | E14: 1 | F14: 0 | G14: 0 | H14: 1 | I14: =IF(G14=1,Inputs!$C$33,Inputs!$D$23) -> 2 | J14: =IF(E14=1,Inputs!$C$31,Inputs!$F$23) -> 46 | K14: =IF(H14=1,Inputs!$C$34,Inputs!$G$23) -> 0.96 | L14: =IF(F14=1,Inputs!$C$32,1) -> 1 | M14: =IF(D14=1,Inputs!$C$30,Inputs!$I$23) -> 0.905 | N14: =I14*Inputs!$B$6*L14*K14*Inputs!$H$23/(J14/Inputs!$B$9) -> 11540.035 | O14: =Inputs!$I$19*Inputs!$I$20*Inputs!$I$21*Inputs!$I$22*M14*Inputs!$I$24*Inputs!$I$25 -> 0.85877154 | P14: =BaseAnalysis!$K$5 -> 16780.8 | Q14: =BaseAnalysis!$K$6 -> 12904.894 | R14: =BaseAnalysis!$K$7 -> 12816.166 | S14: =BaseAnalysis!$K$8 -> 14243.713 | T14: =N14/BaseAnalysis!$D$9 -> 12136.935 | U14: =BaseAnalysis!$F$10/(BaseAnalysis!$D$9*M14) -> 14364.209 | V14: =BaseAnalysis!$F$11/(BaseAnalysis!$D$9*M14*Inputs!$I$24) -> 24698.22 | W14: =MIN(P14:V14) -> 12136.935 | X14: =INDEX($P$4:$V$4,MATCH(W14,P14:V14,0)) -> Anodising (rack batch) | Y14: =W14*O14 -> 10422.854 | Z14: =MIN(Y14,Inputs!$B$7) -> 10000 | AA14: =Z14-$Z$5 -> 1067.9144 | AB14: =Inputs!$B$7/O14 -> 11644.541 | AC14: =Y14/Inputs!$B$7-1 -> 0.042285446 | AD14: =C14*Inputs!$E$29+D14*Inputs!$E$30+E14*Inputs!$E$31+F14*Inputs!$E$32+G14*Inputs!$E$33+H14*Inputs!$E$34 -> 60000 | AE14: =C14*Inputs!$F$29+D14*Inputs!$F$30+E14*Inputs!$F$31+F14*Inputs!$F$32+G14*Inputs!$F$33+H14*Inputs!$F$34 -> 35000
A15: C10 | B15: Capex route: DBR + third line | C15: 1 | D15: 0 | E15: 0 | F15: 0 | G15: 1 | H15: 0 | I15: =IF(G15=1,Inputs!$C$33,Inputs!$D$23) -> 3 | J15: =IF(E15=1,Inputs!$C$31,Inputs!$F$23) -> 52 | K15: =IF(H15=1,Inputs!$C$34,Inputs!$G$23) -> 0.93 | L15: =IF(F15=1,Inputs!$C$32,1) -> 1 | M15: =IF(D15=1,Inputs!$C$30,Inputs!$I$23) -> 0.905 | N15: =I15*Inputs!$B$6*L15*K15*Inputs!$H$23/(J15/Inputs!$B$9) -> 14834.215 | O15: =Inputs!$I$19*Inputs!$I$20*Inputs!$I$21*Inputs!$I$22*M15*Inputs!$I$24*Inputs!$I$25 -> 0.85877154 | P15: =BaseAnalysis!$K$5 -> 16780.8 | Q15: =BaseAnalysis!$K$6 -> 12904.894 | R15: =BaseAnalysis!$K$7 -> 12816.166 | S15: =BaseAnalysis!$K$8 -> 14243.713 | T15: =N15/BaseAnalysis!$D$9 -> 15601.505 | U15: =BaseAnalysis!$F$10/(BaseAnalysis!$D$9*M15) -> 14364.209 | V15: =BaseAnalysis!$F$11/(BaseAnalysis!$D$9*M15*Inputs!$I$24) -> 24698.22 | W15: =MIN(P15:V15) -> 12816.166 | X15: =INDEX($P$4:$V$4,MATCH(W15,P15:V15,0)) -> CNC OP20 finish | Y15: =W15*O15 -> 11006.159 | Z15: =MIN(Y15,Inputs!$B$7) -> 10000 | AA15: =Z15-$Z$5 -> 1067.9144 | AB15: =Inputs!$B$7/O15 -> 11644.541 | AC15: =Y15/Inputs!$B$7-1 -> 0.10061589 | AD15: =C15*Inputs!$E$29+D15*Inputs!$E$30+E15*Inputs!$E$31+F15*Inputs!$E$32+G15*Inputs!$E$33+H15*Inputs!$E$34 -> 460000 | AE15: =C15*Inputs!$F$29+D15*Inputs!$F$30+E15*Inputs!$F$31+F15*Inputs!$F$32+G15*Inputs!$F$33+H15*Inputs!$F$34 -> 90000
A16: C11 | B16: All fixes | C16: 1 | D16: 1 | E16: 1 | F16: 1 | G16: 1 | H16: 1 | I16: =IF(G16=1,Inputs!$C$33,Inputs!$D$23) -> 3 | J16: =IF(E16=1,Inputs!$C$31,Inputs!$F$23) -> 46 | K16: =IF(H16=1,Inputs!$C$34,Inputs!$G$23) -> 0.96 | L16: =IF(F16=1,Inputs!$C$32,1) -> 1.1666667 | M16: =IF(D16=1,Inputs!$C$30,Inputs!$I$23) -> 0.935 | N16: =I16*Inputs!$B$6*L16*K16*Inputs!$H$23/(J16/Inputs!$B$9) -> 20195.061 | O16: =Inputs!$I$19*Inputs!$I$20*Inputs!$I$21*Inputs!$I$22*M16*Inputs!$I$24*Inputs!$I$25 -> 0.8872391 | P16: =BaseAnalysis!$K$5 -> 16780.8 | Q16: =BaseAnalysis!$K$6 -> 12904.894 | R16: =BaseAnalysis!$K$7 -> 12816.166 | S16: =BaseAnalysis!$K$8 -> 14243.713 | T16: =N16/BaseAnalysis!$D$9 -> 21239.637 | U16: =BaseAnalysis!$F$10/(BaseAnalysis!$D$9*M16) -> 13903.326 | V16: =BaseAnalysis!$F$11/(BaseAnalysis!$D$9*M16*Inputs!$I$24) -> 23905.764 | W16: =MIN(P16:V16) -> 12816.166 | X16: =INDEX($P$4:$V$4,MATCH(W16,P16:V16,0)) -> CNC OP20 finish | Y16: =W16*O16 -> 11371.004 | Z16: =MIN(Y16,Inputs!$B$7) -> 10000 | AA16: =Z16-$Z$5 -> 1067.9144 | AB16: =Inputs!$B$7/O16 -> 11270.919 | AC16: =Y16/Inputs!$B$7-1 -> 0.13710039 | AD16: =C16*Inputs!$E$29+D16*Inputs!$E$30+E16*Inputs!$E$31+F16*Inputs!$E$32+G16*Inputs!$E$33+H16*Inputs!$E$34 -> 530000 | AE16: =C16*Inputs!$F$29+D16*Inputs!$F$30+E16*Inputs!$F$31+F16*Inputs!$F$32+G16*Inputs!$F$33+H16*Inputs!$F$34 -> 305000

Sheet SimResults
A1: SimPy simulation results (pasted from simulate.py / run_experiments.py)
A2: SIMULATED DATA. 8 replications per scenario (seeds 2026-2033), 8 weeks with 2 warm-up. Rope size 400 units. Blue = pasted outputs.
A4: ID | B4: Scenario | C4: Release | D4: Good units/wk (mean) | E4: Std dev | F4: 95% CI +/- | G4: Avg WIP (units) | H4: Flow time (hours) | I4: Anodising busy % | J4: Blank saw | K4: CNC OP10 rough | L4: CNC OP20 finish | M4: Deburr / polish | N4: Inspection | O4: Packing | Q4: Rope used (units)
A5: C0 | B5: Base case (push release) | C5: PUSH | D5: 8938 | E5: 43.3 | F5: 36.2 | G5: 6268.9 | H5: 67.36 | I5: 0.93 | J5: 0.639 | K5: 0.812 | L5: 0.818 | M5: 0.777 | N5: 0.695 | O5: 0.409
A6: C1 | B6: DBR release only | C6: DBR | D6: 8937.8 | E6: 43.2 | F6: 36.1 | G6: 495 | H6: 5.32 | I6: 0.93 | J6: 0.571 | K6: 0.725 | L6: 0.731 | M6: 0.694 | N6: 0.696 | O6: 0.409 | Q6: 400
A7: C2 | B7: Anodising yield 90.5% to 93.5% | C7: PUSH | D7: 9235.5 | E7: 38.9 | F7: 32.5 | G7: 4505.6 | H7: 46.86 | I7: 0.93 | J7: 0.618 | K7: 0.786 | L7: 0.791 | M7: 0.752 | N7: 0.719 | O7: 0.422
A8: C3 | B8: SMED: rack batch 52 to 46 min | C8: PUSH | D8: 9969.1 | E8: 73.8 | F8: 61.7 | G8: 605.8 | H8: 5.84 | I8: 0.919 | J8: 0.639 | K8: 0.812 | L8: 0.818 | M8: 0.777 | N8: 0.776 | O8: 0.456
A9: C4 | B9: Anodising 7 days a week | C9: PUSH | D9: 9987.3 | E9: 31.3 | F9: 26.1 | G9: 394.8 | H9: 3.8 | I9: 0.89 | J9: 0.639 | K9: 0.812 | L9: 0.818 | M9: 0.777 | N9: 0.778 | O9: 0.456
A10: C5 | B10: Add third anodising line | C10: PUSH | D10: 9999.4 | E10: 12.9 | F10: 10.8 | G10: 331.4 | H10: 3.18 | I10: 0.694 | J10: 0.639 | K10: 0.812 | L10: 0.818 | M10: 0.777 | N10: 0.778 | O10: 0.457
A11: C6 | B11: TPM: anodising availability 96% | C11: PUSH | D11: 9207.1 | E11: 81.9 | F11: 68.5 | G11: 4643.9 | H11: 48.43 | I11: 0.959 | J11: 0.639 | K11: 0.812 | L11: 0.818 | M11: 0.777 | N11: 0.717 | O11: 0.42
A12: C7 | B12: Low-cost package: DBR + SMED | C12: DBR | D12: 9967.4 | E12: 74.1 | F12: 61.9 | G12: 546.3 | H12: 5.27 | I12: 0.919 | J12: 0.637 | K12: 0.81 | L12: 0.815 | M12: 0.775 | N12: 0.776 | O12: 0.455 | Q12: 900
A13: C8 | B13: DBR + SMED + yield at constraint | C13: DBR | D13: 9991.4 | E13: 23.6 | F13: 19.8 | G13: 396 | H13: 3.81 | I13: 0.891 | J13: 0.618 | K13: 0.786 | L13: 0.791 | M13: 0.751 | N13: 0.778 | O13: 0.457 | Q13: 900
A14: C9 | B14: DBR + SMED + TPM | C14: DBR | D14: 10000 | E14: 34.8 | F14: 29.1 | G14: 365.5 | H14: 3.51 | I14: 0.921 | J14: 0.639 | K14: 0.812 | L14: 0.818 | M14: 0.777 | N14: 0.778 | O14: 0.457 | Q14: 900
A15: C10 | B15: Capex route: DBR + third line | C15: DBR | D15: 9999.4 | E15: 12.9 | F15: 10.8 | G15: 331.4 | H15: 3.18 | I15: 0.694 | J15: 0.639 | K15: 0.812 | L15: 0.818 | M15: 0.777 | N15: 0.778 | O15: 0.457 | Q15: 900
A16: C11 | B16: All fixes | C16: DBR | D16: 10000.9 | E16: 15.4 | F16: 12.9 | G16: 276.4 | H16: 2.65 | I16: 0.509 | J16: 0.618 | K16: 0.786 | L16: 0.791 | M16: 0.752 | N16: 0.778 | O16: 0.457 | Q16: 900
A18: Rope (buffer) size sweep: drum-buffer-rope release with base-case capacity
B19: Rope (units ahead of constraint) | D19: Good units/wk (mean) | E19: Std dev | F19: 95% CI +/- | G19: Avg WIP (units) | H19: Flow time (hours) | I19: Anodising busy %
B20: 150 | D20: 8033.6 | E20: 82 | F20: 86.7 | G20: 244.1 | H20: 2.92 | I20: 0.835
B21: 250 | D21: 8895.2 | E21: 70.1 | F21: 74.1 | G21: 345.1 | H21: 3.72 | I21: 0.925
B22: 400 | D22: 8946.6 | E22: 50.5 | F22: 53.4 | G22: 494.9 | H22: 5.31 | I22: 0.93
B23: 600 | D23: 8946.5 | E23: 50.7 | F23: 53.6 | G23: 694.9 | H23: 7.46 | I23: 0.93
B24: 900 | D24: 8946.5 | E24: 50.7 | F24: 53.6 | G24: 994.9 | H24: 10.68 | I24: 0.93
B25: 1500 | D25: 8946.5 | E25: 50.7 | F25: 53.6 | G25: 1595 | H25: 17.12 | I25: 0.93
A27: Busy % excludes repair time. Under push release the anodising queue grows without bound when the constraint is overloaded, so WIP and flow time are time-averages over the measurement window and keep rising with run length.
A29: Rope re-sizing after the constraint is sped up (DBR + SMED scenario)
B30: Rope (units ahead of constraint) | D30: Good units/wk (mean) | E30: Std dev | F30: 95% CI +/- | G30: Avg WIP (units) | H30: Flow time (hours) | I30: Anodising busy %
B31: 400 | D31: 9839.2 | E31: 91.4 | F31: 96.7 | G31: 390.1 | H31: 3.81 | I31: 0.905
B32: 600 | D32: 9933.2 | E32: 80.1 | F32: 84.8 | G32: 464.1 | H32: 4.49 | I32: 0.915
B33: 900 | D33: 9968.5 | E33: 65.4 | F33: 69.2 | G33: 522.3 | H33: 5.03 | I33: 0.918
B34: 1500 | D34: 9971.4 | E34: 64.8 | F34: 68.6 | G34: 532.6 | H34: 5.13 | I34: 0.918
A36: Lesson: a rope sized for the slow constraint starves it once capacity improves. Re-size the buffer after every exploit or elevate step (step 5).

Sheet Economics
A1: Gain versus cost (module level, USD)
A2: Gain uses simulated output, capped at demand. Net benefit = annual contribution gain - annualised cost. Full-line column scales by the module count on Inputs.
A4: ID | B4: Scenario | C4: Sim good units/wk | D4: Sellable (capped) | E4: Gain vs base (units/wk) | F4: Gain (units/yr) | G4: Contribution gain (USD/yr) | H4: One-time cost (USD) | I4: Annual cost (USD) | J4: Annualised cost (USD/yr) | K4: Net annual benefit (USD) | L4: Payback (months) | M4: WIP vs base | N4: Flow time (h) | O4: Theory sellable (units/wk) | P4: Demand (units/wk) | Q4: Rank by net benefit | R4: Full-line net benefit (USD/yr)
A5: =Fixes!A5 -> C0 | B5: =Fixes!B5 -> Base case (push release) | C5: =INDEX(SimResults!$D$5:$D$16,MATCH($A5,SimResults!$A$5:$A$16,0)) -> 8938 | D5: =MIN(C5,Inputs!$B$7) -> 8938 | E5: =D5-$D$5 -> 0 | F5: =E5*Inputs!$B$8 -> 0 | G5: =F5*Inputs!$B$13 -> 0 | H5: =Fixes!AD5 -> 0 | I5: =Fixes!AE5 -> 0 | J5: =H5/Inputs!$B$14+I5 -> 0 | K5: =G5-J5 -> 0 | L5: =IF(H5=0,0,IF(G5-I5>0,H5/((G5-I5)/12),"n/a")) -> 0 | M5: =INDEX(SimResults!$G$5:$G$16,MATCH($A5,SimResults!$A$5:$A$16,0))/SimResults!$G$5-1 -> 0 | N5: =INDEX(SimResults!$H$5:$H$16,MATCH($A5,SimResults!$A$5:$A$16,0)) -> 67.36 | O5: =Fixes!Z5 -> 8932.0856 | P5: =Inputs!$B$7 -> 10000 | Q5: =RANK(K5,$K$5:$K$16,0) -> 7 | R5: =K5*Inputs!$B$15 -> 0
A6: =Fixes!A6 -> C1 | B6: =Fixes!B6 -> DBR release only | C6: =INDEX(SimResults!$D$5:$D$16,MATCH($A6,SimResults!$A$5:$A$16,0)) -> 8937.8 | D6: =MIN(C6,Inputs!$B$7) -> 8937.8 | E6: =D6-$D$5 -> -0.2 | F6: =E6*Inputs!$B$8 -> -10 | G6: =F6*Inputs!$B$13 -> -33.58 | H6: =Fixes!AD6 -> 10000 | I6: =Fixes!AE6 -> 0 | J6: =H6/Inputs!$B$14+I6 -> 3333.3333 | K6: =G6-J6 -> -3366.9133 | L6: =IF(H6=0,0,IF(G6-I6>0,H6/((G6-I6)/12),"n/a")) -> n/a | M6: =INDEX(SimResults!$G$5:$G$16,MATCH($A6,SimResults!$A$5:$A$16,0))/SimResults!$G$5-1 -> -0.92103878 | N6: =INDEX(SimResults!$H$5:$H$16,MATCH($A6,SimResults!$A$5:$A$16,0)) -> 5.32 | O6: =Fixes!Z6 -> 8932.0856 | P6: =Inputs!$B$7 -> 10000 | Q6: =RANK(K6,$K$5:$K$16,0) -> 8 | R6: =K6*Inputs!$B$15 -> -33669.133
A7: =Fixes!A7 -> C2 | B7: =Fixes!B7 -> Anodising yield 90.5% to 93.5% | C7: =INDEX(SimResults!$D$5:$D$16,MATCH($A7,SimResults!$A$5:$A$16,0)) -> 9235.5 | D7: =MIN(C7,Inputs!$B$7) -> 9235.5 | E7: =D7-$D$5 -> 297.5 | F7: =E7*Inputs!$B$8 -> 14875 | G7: =F7*Inputs!$B$13 -> 49950.25 | H7: =Fixes!AD7 -> 20000 | I7: =Fixes!AE7 -> 60000 | J7: =H7/Inputs!$B$14+I7 -> 66666.667 | K7: =G7-J7 -> -16716.417 | L7: =IF(H7=0,0,IF(G7-I7>0,H7/((G7-I7)/12),"n/a")) -> n/a | M7: =INDEX(SimResults!$G$5:$G$16,MATCH($A7,SimResults!$A$5:$A$16,0))/SimResults!$G$5-1 -> -0.28127742 | N7: =INDEX(SimResults!$H$5:$H$16,MATCH($A7,SimResults!$A$5:$A$16,0)) -> 46.86 | O7: =Fixes!Z7 -> 9228.1768 | P7: =Inputs!$B$7 -> 10000 | Q7: =RANK(K7,$K$5:$K$16,0) -> 9 | R7: =K7*Inputs!$B$15 -> -167164.17
A8: =Fixes!A8 -> C3 | B8: =Fixes!B8 -> SMED: rack batch 52 to 46 min | C8: =INDEX(SimResults!$D$5:$D$16,MATCH($A8,SimResults!$A$5:$A$16,0)) -> 9969.1 | D8: =MIN(C8,Inputs!$B$7) -> 9969.1 | E8: =D8-$D$5 -> 1031.1 | F8: =E8*Inputs!$B$8 -> 51555 | G8: =F8*Inputs!$B$13 -> 173121.69 | H8: =Fixes!AD8 -> 40000 | I8: =Fixes!AE8 -> 0 | J8: =H8/Inputs!$B$14+I8 -> 13333.333 | K8: =G8-J8 -> 159788.36 | L8: =IF(H8=0,0,IF(G8-I8>0,H8/((G8-I8)/12),"n/a")) -> 2.7726162 | M8: =INDEX(SimResults!$G$5:$G$16,MATCH($A8,SimResults!$A$5:$A$16,0))/SimResults!$G$5-1 -> -0.90336423 | N8: =INDEX(SimResults!$H$5:$H$16,MATCH($A8,SimResults!$A$5:$A$16,0)) -> 5.84 | O8: =Fixes!Z8 -> 10000 | P8: =Inputs!$B$7 -> 10000 | Q8: =RANK(K8,$K$5:$K$16,0) -> 1 | R8: =K8*Inputs!$B$15 -> 1597883.6
A9: =Fixes!A9 -> C4 | B9: =Fixes!B9 -> Anodising 7 days a week | C9: =INDEX(SimResults!$D$5:$D$16,MATCH($A9,SimResults!$A$5:$A$16,0)) -> 9987.3 | D9: =MIN(C9,Inputs!$B$7) -> 9987.3 | E9: =D9-$D$5 -> 1049.3 | F9: =E9*Inputs!$B$8 -> 52465 | G9: =F9*Inputs!$B$13 -> 176177.47 | H9: =Fixes!AD9 -> 0 | I9: =Fixes!AE9 -> 120000 | J9: =H9/Inputs!$B$14+I9 -> 120000 | K9: =G9-J9 -> 56177.47 | L9: =IF(H9=0,0,IF(G9-I9>0,H9/((G9-I9)/12),"n/a")) -> 0 | M9: =INDEX(SimResults!$G$5:$G$16,MATCH($A9,SimResults!$A$5:$A$16,0))/SimResults!$G$5-1 -> -0.93702244 | N9: =INDEX(SimResults!$H$5:$H$16,MATCH($A9,SimResults!$A$5:$A$16,0)) -> 3.8 | O9: =Fixes!Z9 -> 10000 | P9: =Inputs!$B$7 -> 10000 | Q9: =RANK(K9,$K$5:$K$16,0) -> 5 | R9: =K9*Inputs!$B$15 -> 561774.7
A10: =Fixes!A10 -> C5 | B10: =Fixes!B10 -> Add third anodising line | C10: =INDEX(SimResults!$D$5:$D$16,MATCH($A10,SimResults!$A$5:$A$16,0)) -> 9999.4 | D10: =MIN(C10,Inputs!$B$7) -> 9999.4 | E10: =D10-$D$5 -> 1061.4 | F10: =E10*Inputs!$B$8 -> 53070 | G10: =F10*Inputs!$B$13 -> 178209.06 | H10: =Fixes!AD10 -> 450000 | I10: =Fixes!AE10 -> 90000 | J10: =H10/Inputs!$B$14+I10 -> 240000 | K10: =G10-J10 -> -61790.94 | L10: =IF(H10=0,0,IF(G10-I10>0,H10/((G10-I10)/12),"n/a")) -> 61.218201 | M10: =INDEX(SimResults!$G$5:$G$16,MATCH($A10,SimResults!$A$5:$A$16,0))/SimResults!$G$5-1 -> -0.94713586 | N10: =INDEX(SimResults!$H$5:$H$16,MATCH($A10,SimResults!$A$5:$A$16,0)) -> 3.18 | O10: =Fixes!Z10 -> 10000 | P10: =Inputs!$B$7 -> 10000 | Q10: =RANK(K10,$K$5:$K$16,0) -> 10 | R10: =K10*Inputs!$B$15 -> -617909.4
A11: =Fixes!A11 -> C6 | B11: =Fixes!B11 -> TPM: anodising availability 96% | C11: =INDEX(SimResults!$D$5:$D$16,MATCH($A11,SimResults!$A$5:$A$16,0)) -> 9207.1 | D11: =MIN(C11,Inputs!$B$7) -> 9207.1 | E11: =D11-$D$5 -> 269.1 | F11: =E11*Inputs!$B$8 -> 13455 | G11: =F11*Inputs!$B$13 -> 45181.89 | H11: =Fixes!AD11 -> 10000 | I11: =Fixes!AE11 -> 35000 | J11: =H11/Inputs!$B$14+I11 -> 38333.333 | K11: =G11-J11 -> 6848.5567 | L11: =IF(H11=0,0,IF(G11-I11>0,H11/((G11-I11)/12),"n/a")) -> 11.785631 | M11: =INDEX(SimResults!$G$5:$G$16,MATCH($A11,SimResults!$A$5:$A$16,0))/SimResults!$G$5-1 -> -0.25921613 | N11: =INDEX(SimResults!$H$5:$H$16,MATCH($A11,SimResults!$A$5:$A$16,0)) -> 48.43 | O11: =Fixes!Z11 -> 9220.2174 | P11: =Inputs!$B$7 -> 10000 | Q11: =RANK(K11,$K$5:$K$16,0) -> 6 | R11: =K11*Inputs!$B$15 -> 68485.567
A12: =Fixes!A12 -> C7 | B12: =Fixes!B12 -> Low-cost package: DBR + SMED | C12: =INDEX(SimResults!$D$5:$D$16,MATCH($A12,SimResults!$A$5:$A$16,0)) -> 9967.4 | D12: =MIN(C12,Inputs!$B$7) -> 9967.4 | E12: =D12-$D$5 -> 1029.4 | F12: =E12*Inputs!$B$8 -> 51470 | G12: =F12*Inputs!$B$13 -> 172836.26 | H12: =Fixes!AD12 -> 50000 | I12: =Fixes!AE12 -> 0 | J12: =H12/Inputs!$B$14+I12 -> 16666.667 | K12: =G12-J12 -> 156169.59 | L12: =IF(H12=0,0,IF(G12-I12>0,H12/((G12-I12)/12),"n/a")) -> 3.4714938 | M12: =INDEX(SimResults!$G$5:$G$16,MATCH($A12,SimResults!$A$5:$A$16,0))/SimResults!$G$5-1 -> -0.91285552 | N12: =INDEX(SimResults!$H$5:$H$16,MATCH($A12,SimResults!$A$5:$A$16,0)) -> 5.27 | O12: =Fixes!Z12 -> 10000 | P12: =Inputs!$B$7 -> 10000 | Q12: =RANK(K12,$K$5:$K$16,0) -> 2 | R12: =K12*Inputs!$B$15 -> 1561695.9
A13: =Fixes!A13 -> C8 | B13: =Fixes!B13 -> DBR + SMED + yield at constraint | C13: =INDEX(SimResults!$D$5:$D$16,MATCH($A13,SimResults!$A$5:$A$16,0)) -> 9991.4 | D13: =MIN(C13,Inputs!$B$7) -> 9991.4 | E13: =D13-$D$5 -> 1053.4 | F13: =E13*Inputs!$B$8 -> 52670 | G13: =F13*Inputs!$B$13 -> 176865.86 | H13: =Fixes!AD13 -> 70000 | I13: =Fixes!AE13 -> 60000 | J13: =H13/Inputs!$B$14+I13 -> 83333.333 | K13: =G13-J13 -> 93532.527 | L13: =IF(H13=0,0,IF(G13-I13>0,H13/((G13-I13)/12),"n/a")) -> 7.1877279 | M13: =INDEX(SimResults!$G$5:$G$16,MATCH($A13,SimResults!$A$5:$A$16,0))/SimResults!$G$5-1 -> -0.93683102 | N13: =INDEX(SimResults!$H$5:$H$16,MATCH($A13,SimResults!$A$5:$A$16,0)) -> 3.81 | O13: =Fixes!Z13 -> 10000 | P13: =Inputs!$B$7 -> 10000 | Q13: =RANK(K13,$K$5:$K$16,0) -> 4 | R13: =K13*Inputs!$B$15 -> 935325.27
A14: =Fixes!A14 -> C9 | B14: =Fixes!B14 -> DBR + SMED + TPM | C14: =INDEX(SimResults!$D$5:$D$16,MATCH($A14,SimResults!$A$5:$A$16,0)) -> 10000 | D14: =MIN(C14,Inputs!$B$7) -> 10000 | E14: =D14-$D$5 -> 1062 | F14: =E14*Inputs!$B$8 -> 53100 | G14: =F14*Inputs!$B$13 -> 178309.8 | H14: =Fixes!AD14 -> 60000 | I14: =Fixes!AE14 -> 35000 | J14: =H14/Inputs!$B$14+I14 -> 55000 | K14: =G14-J14 -> 123309.8 | L14: =IF(H14=0,0,IF(G14-I14>0,H14/((G14-I14)/12),"n/a")) -> 5.0240807 | M14: =INDEX(SimResults!$G$5:$G$16,MATCH($A14,SimResults!$A$5:$A$16,0))/SimResults!$G$5-1 -> -0.94169631 | N14: =INDEX(SimResults!$H$5:$H$16,MATCH($A14,SimResults!$A$5:$A$16,0)) -> 3.51 | O14: =Fixes!Z14 -> 10000 | P14: =Inputs!$B$7 -> 10000 | Q14: =RANK(K14,$K$5:$K$16,0) -> 3 | R14: =K14*Inputs!$B$15 -> 1233098
A15: =Fixes!A15 -> C10 | B15: =Fixes!B15 -> Capex route: DBR + third line | C15: =INDEX(SimResults!$D$5:$D$16,MATCH($A15,SimResults!$A$5:$A$16,0)) -> 9999.4 | D15: =MIN(C15,Inputs!$B$7) -> 9999.4 | E15: =D15-$D$5 -> 1061.4 | F15: =E15*Inputs!$B$8 -> 53070 | G15: =F15*Inputs!$B$13 -> 178209.06 | H15: =Fixes!AD15 -> 460000 | I15: =Fixes!AE15 -> 90000 | J15: =H15/Inputs!$B$14+I15 -> 243333.33 | K15: =G15-J15 -> -65124.273 | L15: =IF(H15=0,0,IF(G15-I15>0,H15/((G15-I15)/12),"n/a")) -> 62.578606 | M15: =INDEX(SimResults!$G$5:$G$16,MATCH($A15,SimResults!$A$5:$A$16,0))/SimResults!$G$5-1 -> -0.94713586 | N15: =INDEX(SimResults!$H$5:$H$16,MATCH($A15,SimResults!$A$5:$A$16,0)) -> 3.18 | O15: =Fixes!Z15 -> 10000 | P15: =Inputs!$B$7 -> 10000 | Q15: =RANK(K15,$K$5:$K$16,0) -> 11 | R15: =K15*Inputs!$B$15 -> -651242.73
A16: =Fixes!A16 -> C11 | B16: =Fixes!B16 -> All fixes | C16: =INDEX(SimResults!$D$5:$D$16,MATCH($A16,SimResults!$A$5:$A$16,0)) -> 10000.9 | D16: =MIN(C16,Inputs!$B$7) -> 10000 | E16: =D16-$D$5 -> 1062 | F16: =E16*Inputs!$B$8 -> 53100 | G16: =F16*Inputs!$B$13 -> 178309.8 | H16: =Fixes!AD16 -> 530000 | I16: =Fixes!AE16 -> 305000 | J16: =H16/Inputs!$B$14+I16 -> 481666.67 | K16: =G16-J16 -> -303356.87 | L16: =IF(H16=0,0,IF(G16-I16>0,H16/((G16-I16)/12),"n/a")) -> n/a | M16: =INDEX(SimResults!$G$5:$G$16,MATCH($A16,SimResults!$A$5:$A$16,0))/SimResults!$G$5-1 -> -0.95590933 | N16: =INDEX(SimResults!$H$5:$H$16,MATCH($A16,SimResults!$A$5:$A$16,0)) -> 2.65 | O16: =Fixes!Z16 -> 10000 | P16: =Inputs!$B$7 -> 10000 | Q16: =RANK(K16,$K$5:$K$16,0) -> 12 | R16: =K16*Inputs!$B$15 -> -3033568.7
A18: Reading the table: fixes at the constraint pay back fast; adding capacity (third line, 7-day working) costs more than the demand-capped gain once the cheap fixes exist. Recovered WIP and lead-time gains from DBR are real but are not converted to dollars here.

Sheet Sources
A1: Sources and basis
A2: The line is simulated. Benchmarks inform plausible ranges only; nothing here describes a real plant.
A4: Ref | B4: Source | C4: Used for | D4: URL / reference
A5: W1 | B5: Fabrico: OEE benchmark guide (world-class 85% = 90% availability x 95% performance x 99.9% quality; typical about 60%) | C5: Plausible availability and performance ranges for stages | D5: https://www.fabrico.io/blog/oee-benchmark/
A6: W2 | B6: TeepTrak: world-class OEE benchmark (metal fabrication and general machining: world-class 80-85%, average 55-65%) | C6: Sanity-check on machining-stage OEE | D6: https://teeptrak.com/en/world-class-oee-benchmark/
A7: W3 | B7: Tractian: what is world-class OEE (Nakajima TPM benchmarks) | C7: OEE definition: availability x performance x quality | D7: https://tractian.com/en/blog/world-class-oee
A8: W4 | B8: SimPy documentation: discrete-event simulation in Python | C8: Simulation framework | D8: https://simpy.readthedocs.io/
A9: B1 | B9: Goldratt and Cox, The Goal (1984); Goldratt, Theory of Constraints and the Five Focusing Steps; drum-buffer-rope scheduling | C9: Method: identify, exploit, subordinate, elevate, repeat; DBR release | D9: Book reference (no URL)
A10: P1 | B10: Project 1: TCO and scenario model, aluminium enclosure (India base case) | C10: Ex-works price, net material cost, and the 86% first-pass yield used as the base line yield | D10: Apple_Sourcing_TCO_Model_Aluminium_Enclosure.xlsx
A11: P2 | B11: Project 2: localization gap and supplier risk dashboard | C11: Context: capacity ramp and yield are top-three risks for Indian enclosure suppliers | D11: Enclosure_Localization_Supplier_Risk_Dashboard.xlsx
A12: A1 | B12: ASSUMPTION: all stage cycle times, machine counts, MTTR, fix parameters and fix costs | C12: Illustrative values; replace with time studies and supplier quotes | D12: n/a
