Workbook

Sheet README
B2: Localization Gap and Supplier Risk Map: Mobile Aluminium Enclosures in India
B3: Independent academic project built from public reports. Scores are analyst judgments, not Apple data.
B5: Question | C5: Which parts of the mobile aluminium-enclosure value chain can India make today versus import, which Indian suppliers carry the most risk, and what should a sourcing team do about the top three risks?
B6: Category | C6: Mobile / consumer-electronics aluminium enclosures (metal housings and chassis). Chosen because enclosures are the most heavily incentivised component category under India's ECMS and the one with the largest visible import gap (extruded aluminium).
B7: Sheets | C7: Dashboard (headline metrics, rankings, charts) > ValueChain (localization gap by stage) > Suppliers (10 suppliers scored on four criteria) > Risks (register, ranking, heat map) > Mitigation (actions for the top three risks) > Sources.
B8: Scoring logic | C8: Supplier risk score = weighted average of four 1-5 scores (5 = highest risk): single-source exposure, capacity and ramp risk, geopolitical / China-linked exposure, quality and process readiness. Weights are editable. Value-chain gap score = import dependence (1-5) x (6 - India readiness (1-5)), range 1-25. Risk score = likelihood x impact (1-5 each).
B9: How to use | C9: Change only BLUE cells (scores, weights, thresholds, likelihood, impact). Ranks, ratings, KPIs, charts and the heat map recalculate. Yellow = key lever.
B10: Colour code | C10: Blue = input. Black = formula. Green = link to another sheet. Yellow fill = key assumption.
B11: Evidence | C11: Facts about suppliers, ECMS approvals and incidents come from the public reports on the Sources sheet and are cited as [n]. The 1-5 scores are my interpretation of those facts. Rows marked 'Analyst estimate' on ValueChain have no direct public source and should be verified.
B12: Limitations | C12: Press reports can be dated or based on unnamed sources. Plant status changes quickly (check before relying on any single item). Supplier scores compare suppliers with each other; they are not statements about any company's absolute quality.

Sheet Dashboard
A1: Dashboard: localization gap and supplier risk for mobile aluminium enclosures in India
A2: Every figure below is a formula driven by the ValueChain, Suppliers and Risks sheets. Scores are analyst judgments; see README and Sources.
A4: Headline metrics
A5: Suppliers assessed | B5: =COUNTA(Suppliers!$B$10:$B$19) -> 10
A6: Suppliers rated High risk | B6: =COUNTIF(Suppliers!$M$10:$M$19,"High") -> 2
A7: Average supplier risk score (1 low, 5 high) | B7: =AVERAGE(Suppliers!$L$10:$L$19) -> 2.975
A8: Highest-risk supplier | B8: =INDEX(Suppliers!$B$10:$B$19,MATCH(MAX(Suppliers!$L$10:$L$19),Suppliers!$L$10:$L$19,0)) -> Yuzhan Technology (India)
A9: Value-chain stages assessed | B9: =COUNTA(ValueChain!$B$7:$B$15) -> 9
A10: Stages with import dependence of 4 or 5 | B10: =COUNTIF(ValueChain!$E$7:$E$15,">=4") -> 4
A11: Stages with a Critical localization gap | B11: =COUNTIF(ValueChain!$I$7:$I$15,"Critical") -> 3
A12: Largest-gap stage | B12: =INDEX(ValueChain!$B$7:$B$15,MATCH(1,ValueChain!$H$7:$H$15,0)) -> Precision extrusion for enclosures
A14: Top 3 risks (from the risk register)
A15: Risk | B15: Linked stage / supplier | C15: Score | D15: Rank
A16: =INDEX(Risks!$B$5:$B$12,MATCH(1,Risks!$H$5:$H$12,0)) -> Imported aluminium extrusion dependence | B16: =INDEX(Risks!$D$5:$D$12,MATCH(1,Risks!$H$5:$H$12,0)) -> V2; S07 Hindalco | C16: =INDEX(Risks!$G$5:$G$12,MATCH(1,Risks!$H$5:$H$12,0)) -> 20 | D16: 1
A17: =INDEX(Risks!$B$5:$B$12,MATCH(2,Risks!$H$5:$H$12,0)) -> Chinese equipment and engineer dependence | B17: =INDEX(Risks!$D$5:$D$12,MATCH(2,Risks!$H$5:$H$12,0)) -> V4, V8; S02 Yuzhan, S08-S10 | C17: =INDEX(Risks!$G$5:$G$12,MATCH(2,Risks!$H$5:$H$12,0)) -> 20 | D17: 2
A18: =INDEX(Risks!$B$5:$B$12,MATCH(3,Risks!$H$5:$H$12,0)) -> Capacity ramp and execution delay | B18: =INDEX(Risks!$D$5:$D$12,MATCH(3,Risks!$H$5:$H$12,0)) -> V3; S01, S02, S03, S07 | C18: =INDEX(Risks!$G$5:$G$12,MATCH(3,Risks!$H$5:$H$12,0)) -> 16 | D18: 3
A20: Supplier risk ranking (highest risk first)
A21: Supplier | B21: Role in enclosure chain | C21: Risk score | D21: Rating
A22: =1&". "&INDEX(Suppliers!$B$10:$B$19,MATCH(1,Suppliers!$N$10:$N$19,0)) -> 1. Yuzhan Technology (India) | B22: =INDEX(Suppliers!$C$10:$C$19,MATCH(1,Suppliers!$N$10:$N$19,0)) -> iPhone enclosures and display modules | C22: =INDEX(Suppliers!$L$10:$L$19,MATCH(1,Suppliers!$N$10:$N$19,0)) -> 4 | D22: =INDEX(Suppliers!$M$10:$M$19,MATCH(1,Suppliers!$N$10:$N$19,0)) -> High
A23: =2&". "&INDEX(Suppliers!$B$10:$B$19,MATCH(2,Suppliers!$N$10:$N$19,0)) -> 2. Hindalco Industries (extrusion) | B23: =INDEX(Suppliers!$C$10:$C$19,MATCH(2,Suppliers!$N$10:$N$19,0)) -> Precision aluminium extrusion for enclosures | C23: =INDEX(Suppliers!$L$10:$L$19,MATCH(2,Suppliers!$N$10:$N$19,0)) -> 3.75 | D23: =INDEX(Suppliers!$M$10:$M$19,MATCH(2,Suppliers!$N$10:$N$19,0)) -> High
A24: =3&". "&INDEX(Suppliers!$B$10:$B$19,MATCH(3,Suppliers!$N$10:$N$19,0)) -> 3. Tata Electronics (Hosur) | B24: =INDEX(Suppliers!$C$10:$C$19,MATCH(3,Suppliers!$N$10:$N$19,0)) -> iPhone metal enclosures (CNC, finishing) | C24: =INDEX(Suppliers!$L$10:$L$19,MATCH(3,Suppliers!$N$10:$N$19,0)) -> 3 | D24: =INDEX(Suppliers!$M$10:$M$19,MATCH(3,Suppliers!$N$10:$N$19,0)) -> Medium
A25: =4&". "&INDEX(Suppliers!$B$10:$B$19,MATCH(4,Suppliers!$N$10:$N$19,0)) -> 4. TD Connex | B25: =INDEX(Suppliers!$C$10:$C$19,MATCH(4,Suppliers!$N$10:$N$19,0)) -> Micro-precision CNC, injection, stamping, LSR | C25: =INDEX(Suppliers!$L$10:$L$19,MATCH(4,Suppliers!$N$10:$N$19,0)) -> 3 | D25: =INDEX(Suppliers!$M$10:$M$19,MATCH(4,Suppliers!$N$10:$N$19,0)) -> Medium
A26: =5&". "&INDEX(Suppliers!$B$10:$B$19,MATCH(5,Suppliers!$N$10:$N$19,0)) -> 5. Jyoti CNC Automation | B26: =INDEX(Suppliers!$C$10:$C$19,MATCH(5,Suppliers!$N$10:$N$19,0)) -> CNC machine tools | C26: =INDEX(Suppliers!$L$10:$L$19,MATCH(5,Suppliers!$N$10:$N$19,0)) -> 3 | D26: =INDEX(Suppliers!$M$10:$M$19,MATCH(5,Suppliers!$N$10:$N$19,0)) -> Medium
A27: =6&". "&INDEX(Suppliers!$B$10:$B$19,MATCH(6,Suppliers!$N$10:$N$19,0)) -> 6. Motherson Electronic Components | B27: =INDEX(Suppliers!$C$10:$C$19,MATCH(6,Suppliers!$N$10:$N$19,0)) -> Enclosures / mechanical components | C27: =INDEX(Suppliers!$L$10:$L$19,MATCH(6,Suppliers!$N$10:$N$19,0)) -> 2.75 | D27: =INDEX(Suppliers!$M$10:$M$19,MATCH(6,Suppliers!$N$10:$N$19,0)) -> Medium
A28: =7&". "&INDEX(Suppliers!$B$10:$B$19,MATCH(7,Suppliers!$N$10:$N$19,0)) -> 7. Titan Engineering & Automation | B28: =INDEX(Suppliers!$C$10:$C$19,MATCH(7,Suppliers!$N$10:$N$19,0)) -> Capital equipment and automation | C28: =INDEX(Suppliers!$L$10:$L$19,MATCH(7,Suppliers!$N$10:$N$19,0)) -> 2.75 | D28: =INDEX(Suppliers!$M$10:$M$19,MATCH(7,Suppliers!$N$10:$N$19,0)) -> Medium
A29: =8&". "&INDEX(Suppliers!$B$10:$B$19,MATCH(8,Suppliers!$N$10:$N$19,0)) -> 8. Bharat Forge | B29: =INDEX(Suppliers!$C$10:$C$19,MATCH(8,Suppliers!$N$10:$N$19,0)) -> Precision engineering / equipment | C29: =INDEX(Suppliers!$L$10:$L$19,MATCH(8,Suppliers!$N$10:$N$19,0)) -> 2.75 | D29: =INDEX(Suppliers!$M$10:$M$19,MATCH(8,Suppliers!$N$10:$N$19,0)) -> Medium
A30: =9&". "&INDEX(Suppliers!$B$10:$B$19,MATCH(9,Suppliers!$N$10:$N$19,0)) -> 9. Aequs (Aequs Consumer Products) | B30: =INDEX(Suppliers!$C$10:$C$19,MATCH(9,Suppliers!$N$10:$N$19,0)) -> MacBook, Apple Watch and other non-iPhone enclosures | C30: =INDEX(Suppliers!$L$10:$L$19,MATCH(9,Suppliers!$N$10:$N$19,0)) -> 2.5 | D30: =INDEX(Suppliers!$M$10:$M$19,MATCH(9,Suppliers!$N$10:$N$19,0)) -> Medium
A31: =10&". "&INDEX(Suppliers!$B$10:$B$19,MATCH(10,Suppliers!$N$10:$N$19,0)) -> 10. Jabil India | B31: =INDEX(Suppliers!$C$10:$C$19,MATCH(10,Suppliers!$N$10:$N$19,0)) -> AirPods and plastic enclosures | C31: =INDEX(Suppliers!$L$10:$L$19,MATCH(10,Suppliers!$N$10:$N$19,0)) -> 2.25 | D31: =INDEX(Suppliers!$M$10:$M$19,MATCH(10,Suppliers!$N$10:$N$19,0)) -> Low
A33: Context: sourced figures (inputs, not calculated)
A34: Item | B34: Value | C34: Source
A35: ECMS applications approved to date (Aug 2026) | B35: 106 (₹69,548 crore) | C35: [6]
A36: Mobile-enclosure investment in tranche 3 (Jan 2026) | B36: over ₹27,000 crore | C36: [17]
A37: Phone-enclosure extrusion imported today | B37: 100% | C37: [4][8]
A38: Hindalco Kuppam extrusion plant: target start | B38: March 2027 | C38: [7]
A39: Hindalco extrusion capacity with Kuppam + Silvassa | B39: 109,000 t/yr (from 60,000) | C39: [8]
A40: Project 1: India local vs China import landed cost (base) | B40: +9.6% (India dearer) | C40: Project 1 model
A41: Project 1: India first-pass yield needed to match China | B41: about 95% | C41: Project 1 model

Sheet ValueChain
A1: Localization gap map: what India makes today versus imports
A2: Import dependence 1-5 (5 = fully imported). India readiness 1-5 (5 = mature, scaled capacity). Gap score = dependence x (6 - readiness).
A3: Critical from | B3: 15
A4: Elevated from | B4: 9
A6: ID | B6: Value-chain stage | C6: What it is | D6: India status today (public evidence in [ ]) | E6: Import dependence | F6: India readiness | G6: Gap score | H6: Rank | I6: Priority | J6: Evidence strength | K6: Key Indian players / projects | L6: Source ref
A7: V1 | B7: Primary aluminium and alloy | C7: Smelted primary metal and 6xxx-series alloy billet | D7: India has large integrated aluminium producers; Hindalco plans a $10bn five-year expansion including the Dahej smelter. Metal supply is not the constraint; precision extrusion is. | E7: 2 | F7: 4 | G7: =E7*(6-F7) -> 4 | H7: =RANK(G7,$G$7:$G$15,0)+COUNTIF($G$7:G7,G7)-1 -> 9 | I7: =IF(G7>=$B$3,"Critical",IF(G7>=$B$4,"Elevated","Manageable")) -> Manageable | J7: Mixed | K7: Hindalco, Vedanta, NALCO | L7: [8][22]
A8: V2 | B8: Precision extrusion for enclosures | C8: Extruded aluminium profile later machined into the enclosure | D8: 100% imported today per the government's own ECMS release. Hindalco's ₹586 crore Kuppam plant targets March 2027; extrusion capacity to rise 60,000 to 109,000 tonnes a year with Kuppam and Silvassa. | E8: 5 | F8: 2 | G8: =E8*(6-F8) -> 20 | H8: =RANK(G8,$G$7:$G$15,0)+COUNTIF($G$7:G8,G8)-1 -> 1 | I8: =IF(G8>=$B$3,"Critical",IF(G8>=$B$4,"Elevated","Manageable")) -> Critical | J8: Sourced | K8: Hindalco (Kuppam, Silvassa) | L8: [4][7][8]
A9: V3 | B9: CNC machining of enclosures | C9: Precision milling of the extruded or billet blank into the final enclosure | D9: Tata supplies a limited share of iPhone enclosures; Yuzhan, Motherson, Aequs and TD Connex are ramping. Indian suppliers already export mechanical parts and housings to China and Vietnam. | E9: 3 | F9: 3 | G9: =E9*(6-F9) -> 9 | H9: =RANK(G9,$G$7:$G$15,0)+COUNTIF($G$7:G9,G9)-1 -> 5 | I9: =IF(G9>=$B$3,"Critical",IF(G9>=$B$4,"Elevated","Manageable")) -> Elevated | J9: Sourced | K9: Tata Electronics, Yuzhan, Motherson, Aequs, TD Connex | L9: [3][6][9][13]
A10: V4 | B10: CNC machine tools and precision equipment | C10: The machines and tooling that cut and finish enclosures | D10: Equipment shipments to Foxconn's India plants were held up in China in 2025; India lacked technology for some specialised equipment. About 35 Indian firms now make machinery for Apple's supply chain, nearly half engaged in the last two years. | E10: 4 | F10: 2 | G10: =E10*(6-F10) -> 16 | H10: =RANK(G10,$G$7:$G$15,0)+COUNTIF($G$7:G10,G10)-1 -> 2 | I10: =IF(G10>=$B$3,"Critical",IF(G10>=$B$4,"Elevated","Manageable")) -> Critical | J10: Sourced | K10: Titan Engineering & Automation, Jyoti CNC, Bharat Forge, Wipro | L10: [10][11][12]
A11: V5 | B11: Cutting tools, fixtures and consumables | C11: Cutters, jigs, fixtures and wear parts consumed in machining | D11: No direct public source found. Likely tied to the same China-linked equipment ecosystem as V4; treat as an estimate and verify with suppliers. | E11: 4 | F11: 3 | G11: =E11*(6-F11) -> 12 | H11: =RANK(G11,$G$7:$G$15,0)+COUNTIF($G$7:G11,G11)-1 -> 4 | I11: =IF(G11>=$B$3,"Critical",IF(G11>=$B$4,"Elevated","Manageable")) -> Elevated | J11: Analyst estimate | K11: Not identified in sources | L11: n/a
A12: V6 | B12: Surface finishing (anodising and chemistry) | C12: Anodising, dyeing and coating that give the enclosure its finish | D12: No direct public source found. Process chemistry and dyes may rely on imports; treat as an estimate and verify with finishing suppliers. | E12: 3 | F12: 3 | G12: =E12*(6-F12) -> 9 | H12: =RANK(G12,$G$7:$G$15,0)+COUNTIF($G$7:G12,G12)-1 -> 6 | I12: =IF(G12>=$B$3,"Critical",IF(G12>=$B$4,"Elevated","Manageable")) -> Elevated | J12: Analyst estimate | K12: Not identified in sources | L12: n/a
A13: V7 | B13: Plastic and antenna-band moulding, LSR sealing | C13: Injection-moulded antenna splits and liquid silicone seals inside the housing | D13: TD Connex lists plastic injection, liquid silicone rubber and stamping capability at Oragadam; Jabil and Motherson produce plastic and mechanical enclosure parts. | E13: 2 | F13: 3 | G13: =E13*(6-F13) -> 6 | H13: =RANK(G13,$G$7:$G$15,0)+COUNTIF($G$7:G13,G13)-1 -> 8 | I13: =IF(G13>=$B$3,"Critical",IF(G13>=$B$4,"Elevated","Manageable")) -> Manageable | J13: Mixed | K13: TD Connex, Jabil, Motherson | L13: [1][3][15]
A14: V8 | B14: Process know-how and skilled engineers | C14: Line-setup, tool-maintenance and process-engineering skills | D14: Foxconn recalled about 300 Chinese engineers from India in 2025 and began flying in Taiwanese replacements; Beijing reportedly discouraged technology and equipment transfers to India. | E14: 4 | F14: 2 | G14: =E14*(6-F14) -> 16 | H14: =RANK(G14,$G$7:$G$15,0)+COUNTIF($G$7:G14,G14)-1 -> 3 | I14: =IF(G14>=$B$3,"Critical",IF(G14>=$B$4,"Elevated","Manageable")) -> Critical | J14: Sourced | K14: Foxconn, Tata Electronics (training programmes) | L14: [11][23]
A15: V9 | B15: Inspection, metrology and automation | C15: Vision inspection, gauging and line automation | D15: Titan Engineering & Automation and VVDN appear on the reported list of Apple suppliers in India; no capability detail found. Treat as an estimate. | E15: 3 | F15: 3 | G15: =E15*(6-F15) -> 9 | H15: =RANK(G15,$G$7:$G$15,0)+COUNTIF($G$7:G15,G15)-1 -> 7 | I15: =IF(G15>=$B$3,"Critical",IF(G15>=$B$4,"Elevated","Manageable")) -> Elevated | J15: Analyst estimate | K15: Titan Engineering & Automation, VVDN | L15: [12][24]

Sheet Suppliers
A1: Supplier risk scoring: mobile aluminium enclosure chain in India
A2: Scores 1-5 where 5 = highest risk. Weights and thresholds are editable. Scores are analyst judgments based on the cited reports.
A4: Criterion | B4: Single-source exposure | C4: Capacity and ramp risk | D4: Geopolitical / China-linked exposure | E4: Quality and process readiness | F4: Total
A5: Weight | B5: 0.25 | C5: 0.25 | D5: 0.25 | E5: 0.25 | F5: =SUM(B5:E5) -> 1 | G5: =IF(ROUND(F5,6)=1,"Weights sum to 100%","Weights do not sum to 100%: scores are normalised") -> Weights sum to 100%
A6: Medium from | B6: 2.5 | C6: score (below = Low)
A7: High from | B7: 3.5 | C7: score
A9: ID | B9: Supplier | C9: Role in enclosure chain | D9: Tier | E9: Location | F9: Owner / HQ | G9: Apple link and public status (sources in [ ]) | H9: Single-source | I9: Capacity / ramp | J9: Geopolitical | K9: Quality readiness | L9: Weighted risk score | M9: Rating | N9: Rank | O9: Why these scores (analyst judgment on the evidence)
A10: S01 | B10: Tata Electronics (Hosur) | C10: iPhone metal enclosures (CNC, finishing) | D10: Tier-1 | E10: Hosur, Tamil Nadu | F10: Tata Group (India) | G10: Makes iPhone enclosures at Hosur; Foxconn's later entry ended Tata's position as the only local maker [19]. Supplies only a limited share of iPhone enclosures domestically, set to rise [9]. ECMS enclosure approval Jan 2026; Hosur enclosure plant moving to production Aug 2026 [4][6]. Plant restored after a Sept 2024 fire; output reportedly being doubled [2]. | H10: 4 | I10: 3 | J10: 3 | K10: 2 | L10: =SUMPRODUCT(H10:K10,$B$5:$E$5)/$F$5 -> 3 | M10: =IF(L10>=$B$7,"High",IF(L10>=$B$6,"Medium","Low")) -> Medium | N10: =RANK(L10,$L$10:$L$19,0)+COUNTIF($L$10:L10,L10)-1 -> 3 | O10: Single-source 4: long the only local maker and still a limited share of volume [9][19]. Capacity 3: the 2024 fire shows plant-level fragility [2]. Geopolitical 3: Indian-owned, but extrusion is 100% imported and tooling largely Chinese [4][10]. Quality 2: producing iPhone enclosures at volume for several years [18].
A11: S02 | B11: Yuzhan Technology (India) | C11: iPhone enclosures and display modules | D11: Tier-1 | E11: Kanchipuram, Tamil Nadu | F11: Foxconn (Taiwan) | G11: Foxconn's India arm; made enclosures and display modules for older iPhones, not yet iPhone 17, as of mid-2025 [11]. ECMS enclosure approval Jan 2026; Kanchipuram enclosure facility progressing to production (Aug 2026) [4][6]. Foxconn recalled about 300 Chinese engineers from India in 2025 [11]. | H11: 3 | I11: 4 | J11: 5 | K11: 4 | L11: =SUMPRODUCT(H11:K11,$B$5:$E$5)/$F$5 -> 4 | M11: =IF(L11>=$B$7,"High",IF(L11>=$B$6,"Medium","Low")) -> High | N11: =RANK(L11,$L$10:$L$19,0)+COUNTIF($L$10:L11,L11)-1 -> 1 | O11: Single-source 3: second local iPhone enclosure source. Capacity 4: production began only months before mid-2025 and a new plant is still being built [6][11]. Geopolitical 5: engineer recall and held-up equipment shipments hit Foxconn directly [10][11]. Quality 4: not on the latest iPhone line as of mid-2025 [11].
A12: S03 | B12: Motherson Electronic Components | C12: Enclosures / mechanical components | D12: Tier-1 | E12: Kanchipuram, Tamil Nadu | F12: Motherson Group (India) | G12: ECMS enclosure approval Jan 2026; Kanchipuram plant expected to create 5,741 jobs [4][6][20]. Reported to produce mechanical components such as enclosures for Apple products, shipped to China and Vietnam assembly [1]. | H12: 2 | I12: 4 | J12: 2 | K12: 3 | L12: =SUMPRODUCT(H12:K12,$B$5:$E$5)/$F$5 -> 2.75 | M12: =IF(L12>=$B$7,"High",IF(L12>=$B$6,"Medium","Low")) -> Medium | N12: =RANK(L12,$L$10:$L$19,0)+COUNTIF($L$10:L12,L12)-1 -> 6 | O12: Single-source 2: an additional rather than sole source. Capacity 4: large plant still being built [6][20]. Geopolitical 2: Indian group. Quality 3: exporting enclosure parts for several Apple products but metal-enclosure volume not yet proven [1].
A13: S04 | B13: Aequs (Aequs Consumer Products) | C13: MacBook, Apple Watch and other non-iPhone enclosures | D13: Tier-1 | E13: Hubballi, Karnataka | F13: Aequs (India) | G13: Trial production of MacBook enclosures and Apple Watch mechanical parts; formally added to Apple's supply chain [3]. ECMS approval for laptop and smartwatch enclosures [5]. Electronics SEZ cleared June 2025 [3]. | H13: 2 | I13: 3 | J13: 2 | K13: 3 | L13: =SUMPRODUCT(H13:K13,$B$5:$E$5)/$F$5 -> 2.5 | M13: =IF(L13>=$B$7,"High",IF(L13>=$B$6,"Medium","Low")) -> Medium | N13: =RANK(L13,$L$10:$L$19,0)+COUNTIF($L$10:L13,L13)-1 -> 9 | O13: Single-source 2: niche, non-iPhone parts. Capacity 3: trial production, SEZ still being developed [3]. Geopolitical 2: Indian company. Quality 3: qualification under way, volume history limited [3].
A14: S05 | B14: Jabil India | C14: AirPods and plastic enclosures | D14: Tier-1 | E14: Pune, Maharashtra; Trichy, Tamil Nadu (planned) | F14: Jabil Inc. (US) | G14: Produces AirPods components at Pune; may take on plastic AirPods enclosures [1][21]. Announced a plant near Trichy of about ₹2,000 crore ($238M), around 5,000 jobs [14]. | H14: 2 | I14: 3 | J14: 2 | K14: 2 | L14: =SUMPRODUCT(H14:K14,$B$5:$E$5)/$F$5 -> 2.25 | M14: =IF(L14>=$B$7,"High",IF(L14>=$B$6,"Medium","Low")) -> Low | N14: =RANK(L14,$L$10:$L$19,0)+COUNTIF($L$10:L14,L14)-1 -> 10 | O14: Single-source 2: global multi-site firm. Capacity 3: Trichy plant is planned, not yet running [14]. Geopolitical 2: US parent. Quality 2: established global Apple supplier [1].
A15: S06 | B15: TD Connex | C15: Micro-precision CNC, injection, stamping, LSR | D15: Tier-2 | E15: Oragadam, Tamil Nadu | F15: Singapore-based | G15: Operates a unit at Oragadam; preparing a ₹200 crore expansion and about 20 acres for smartphone-housing functions (CNC, injection, stamping, LSR) [3][15]. | H15: 3 | I15: 3 | J15: 3 | K15: 3 | L15: =SUMPRODUCT(H15:K15,$B$5:$E$5)/$F$5 -> 3 | M15: =IF(L15>=$B$7,"High",IF(L15>=$B$6,"Medium","Low")) -> Medium | N15: =RANK(L15,$L$10:$L$19,0)+COUNTIF($L$10:L15,L15)-1 -> 4 | O15: Single-source 3: small niche supplier with few alternates. Capacity 3: expansion planned, land not yet acquired [3]. Geopolitical 3: foreign-owned, ownership structure not verified [15]. Quality 3: capabilities listed but Apple volume history not verified.
A16: S07 | B16: Hindalco Industries (extrusion) | C16: Precision aluminium extrusion for enclosures | D16: Tier-2 (material) | E16: Kuppam, Andhra Pradesh; Silvassa | F16: Aditya Birla Group (India) | G16: Phone-enclosure extrusion is 100% imported today [4][8]. ₹586 crore Kuppam plant for iPhone chassis, production targeted March 2027 [7]. ECMS approval Jan 2026 [4]. Extrusion capacity to rise from 60,000 to 109,000 tonnes a year with Kuppam and Silvassa [8]. | H16: 5 | I16: 4 | J16: 2 | K16: 4 | L16: =SUMPRODUCT(H16:K16,$B$5:$E$5)/$F$5 -> 3.75 | M16: =IF(L16>=$B$7,"High",IF(L16>=$B$6,"Medium","Low")) -> High | N16: =RANK(L16,$L$10:$L$19,0)+COUNTIF($L$10:L16,L16)-1 -> 2 | O16: Single-source 5: the only planned domestic source of a fully imported input [4][8]. Capacity 4: plant not producing until March 2027 [7]. Geopolitical 2: Indian metal. Quality 4: phone-grade precision extrusion is new and still to be qualified.
A17: S08 | B17: Titan Engineering & Automation | C17: Capital equipment and automation | D17: Tier-2 (equipment) | E17: Hosur, Tamil Nadu | F17: Titan Company (Tata Group) | G17: One of the Indian firms supplying capital equipment to Apple's vendors; around 35 Indian firms make machinery for Apple's local supply chain [12]. | H17: 3 | I17: 3 | J17: 2 | K17: 3 | L17: =SUMPRODUCT(H17:K17,$B$5:$E$5)/$F$5 -> 2.75 | M17: =IF(L17>=$B$7,"High",IF(L17>=$B$6,"Medium","Low")) -> Medium | N17: =RANK(L17,$L$10:$L$19,0)+COUNTIF($L$10:L17,L17)-1 -> 7 | O17: Single-source 3: one of about 35 machinery makers [12]. Capacity 3: scaling with Apple vendors. Geopolitical 2: Indian company, reduces China tooling exposure. Quality 3: precision consumer-electronics tooling is a new domain.
A18: S09 | B18: Jyoti CNC Automation | C18: CNC machine tools | D18: Tier-2 (equipment) | E18: Rajkot, Gujarat | F18: Jyoti CNC (India) | G18: Named among Indian firms supplying capital equipment to Apple's vendors as China restricts equipment exports to them [12]. | H18: 3 | I18: 3 | J18: 2 | K18: 4 | L18: =SUMPRODUCT(H18:K18,$B$5:$E$5)/$F$5 -> 3 | M18: =IF(L18>=$B$7,"High",IF(L18>=$B$6,"Medium","Low")) -> Medium | N18: =RANK(L18,$L$10:$L$19,0)+COUNTIF($L$10:L18,L18)-1 -> 5 | O18: Single-source 3: one of about 35 makers [12]. Capacity 3. Geopolitical 2: Indian. Quality 4: local machines unproven at small-format consumer-electronics tolerances; Rest of World reports India lacked the technology for some specialised equipment [10].
A19: S10 | B19: Bharat Forge | C19: Precision engineering / equipment | D19: Tier-2 (equipment) | E19: Pune, Maharashtra | F19: Bharat Forge (India) | G19: Named among Indian firms supplying capital equipment to Apple's vendors [12]. | H19: 3 | I19: 2 | J19: 2 | K19: 4 | L19: =SUMPRODUCT(H19:K19,$B$5:$E$5)/$F$5 -> 2.75 | M19: =IF(L19>=$B$7,"High",IF(L19>=$B$6,"Medium","Low")) -> Medium | N19: =RANK(L19,$L$10:$L$19,0)+COUNTIF($L$10:L19,L19)-1 -> 8 | O19: Single-source 3: one of about 35 makers [12]. Capacity 2: large industrial group. Geopolitical 2: Indian. Quality 4: moving from heavy engineering to consumer-electronics precision is a new domain.

Sheet Risks
A1: Risk register: mobile aluminium enclosure supply chain in India
A2: Likelihood and impact scored 1-5 (analyst judgment). Score = likelihood x impact. Top three are tagged; residual scores assume the Mitigation sheet actions are done.
A4: ID | B4: Risk | C4: Description and evidence (sources in [ ]) | D4: Linked stage / supplier | E4: Likelihood | F4: Impact | G4: Score | H4: Rank | I4: Top 3? | J4: Early-warning indicator | K4: Residual likelihood | L4: Residual impact | M4: Residual score | N4: Reduction
A5: R1 | B5: Imported aluminium extrusion dependence | C5: Extruded aluminium for phone enclosures is 100% imported until Hindalco's Kuppam plant starts (target March 2027). Any trade, tariff or logistics shock hits every enclosure maker at once [4][7][8]. | D5: V2; S07 Hindalco | E5: 4 | F5: 5 | G5: =E5*F5 -> 20 | H5: =RANK(G5,$G$5:$G$12,0)+COUNTIF($G$5:G5,G5)-1 -> 1 | I5: =IF(H5<=3,"TOP 3","") -> TOP 3 | J5: Weeks of extrusion cover; Kuppam commissioning milestones; supplier lead times | K5: 3 | L5: 3 | M5: =IF(AND(ISNUMBER(K5),ISNUMBER(L5)),K5*L5,"") -> 9 | N5: =IF(ISNUMBER(M5),1-M5/G5,"") -> 0.55
A6: R2 | B6: Chinese equipment and engineer dependence | C6: Foxconn recalled about 300 Chinese engineers and equipment shipments were held up in China in 2025; India lacked technology for some specialised equipment [10][11][23]. | D6: V4, V8; S02 Yuzhan, S08-S10 | E6: 4 | F6: 5 | G6: =E6*F6 -> 20 | H6: =RANK(G6,$G$5:$G$12,0)+COUNTIF($G$5:G6,G6)-1 -> 2 | I6: =IF(H6<=3,"TOP 3","") -> TOP 3 | J6: Equipment shipment delays; engineer headcount; share of equipment value from non-China origin | K6: 3 | L6: 4 | M6: =IF(AND(ISNUMBER(K6),ISNUMBER(L6)),K6*L6,"") -> 12 | N6: =IF(ISNUMBER(M6),1-M6/G6,"") -> 0.4
A7: R3 | B7: Capacity ramp and execution delay | C7: Several new enclosure plants (Hindalco Kuppam, Motherson and Yuzhan at Kanchipuram, Tata Hosur) must ramp together; one slip can stall launch volumes [4][6][7]. | D7: V3; S01, S02, S03, S07 | E7: 4 | F7: 4 | G7: =E7*F7 -> 16 | H7: =RANK(G7,$G$5:$G$12,0)+COUNTIF($G$5:G7,G7)-1 -> 3 | I7: =IF(H7<=3,"TOP 3","") -> TOP 3 | J7: Schedule slip in weeks; line OEE; first-pass yield versus plan | K7: 3 | L7: 3 | M7: =IF(AND(ISNUMBER(K7),ISNUMBER(L7)),K7*L7,"") -> 9 | N7: =IF(ISNUMBER(M7),1-M7/G7,"") -> 0.4375
A8: R4 | B8: Single-site concentration and plant incident | C8: Tata's Hosur plant is the main local iPhone enclosure source and had a fire in Sept 2024; one site outage removes most local supply [2][9]. | D8: V3; S01 Tata Electronics | E8: 3 | F8: 5 | G8: =E8*F8 -> 15 | H8: =RANK(G8,$G$5:$G$12,0)+COUNTIF($G$5:G8,G8)-1 -> 4 | I8: =IF(H8<=3,"TOP 3","") | J8: Safety audit findings; days of finished-goods buffer | M8: =IF(AND(ISNUMBER(K8),ISNUMBER(L8)),K8*L8,"") | N8: =IF(ISNUMBER(M8),1-M8/G8,"")
A9: R5 | B9: Yield and quality ramp at new Indian lines | C9: Early lines run below mature-line yield; the TCO model shows India needs about 95% first-pass yield to match China's landed cost at 50% incentive pass-through (Project 1). | D9: V3; S02, S03, S04 | E9: 4 | F9: 3 | G9: =E9*F9 -> 12 | H9: =RANK(G9,$G$5:$G$12,0)+COUNTIF($G$5:G9,G9)-1 -> 5 | I9: =IF(H9<=3,"TOP 3","") | J9: Weekly first-pass yield; scrap rate; customer returns | M9: =IF(AND(ISNUMBER(K9),ISNUMBER(L9)),K9*L9,"") | N9: =IF(ISNUMBER(M9),1-M9/G9,"")
A10: R6 | B10: Policy and incentive risk | C10: ECMS payouts, duty rates and US tariff policy can change; ECMS approvals already exceed the scheme's original target of ₹59,350 crore [6]. | D10: All | E10: 3 | F10: 3 | G10: =E10*F10 -> 9 | H10: =RANK(G10,$G$5:$G$12,0)+COUNTIF($G$5:G10,G10)-1 -> 6 | I10: =IF(H10<=3,"TOP 3","") | J10: Notification changes; ECMS disbursement delays | M10: =IF(AND(ISNUMBER(K10),ISNUMBER(L10)),K10*L10,"") | N10: =IF(ISNUMBER(M10),1-M10/G10,"")
A11: R7 | B11: Skilled labour hiring and attrition | C11: Tata alone planned to add up to 45,000 workers at Hosur; hiring and retention at that scale is an execution risk [18]. | D11: V8; S01 | E11: 3 | F11: 3 | G11: =E11*F11 -> 9 | H11: =RANK(G11,$G$5:$G$12,0)+COUNTIF($G$5:G11,G11)-1 -> 7 | I11: =IF(H11<=3,"TOP 3","") | J11: Attrition rate; training completion rate | M11: =IF(AND(ISNUMBER(K11),ISNUMBER(L11)),K11*L11,"") | N11: =IF(ISNUMBER(M11),1-M11/G11,"")
A12: R8 | B12: Aluminium price volatility | C12: LME cash aluminium moved from $3,248.5 to $3,107 per tonne in one week (28 Sep to 5 Oct 2026) [25]; analysts see $3,200-3,500 average for 2026 [26]. | D12: V1; all | E12: 4 | F12: 2 | G12: =E12*F12 -> 8 | H12: =RANK(G12,$G$5:$G$12,0)+COUNTIF($G$5:G12,G12)-1 -> 8 | I12: =IF(H12<=3,"TOP 3","") | J12: LME price versus contract index band | M12: =IF(AND(ISNUMBER(K12),ISNUMBER(L12)),K12*L12,"") | N12: =IF(ISNUMBER(M12),1-M12/G12,"")
A15: Risk heat map: number of risks in each likelihood x impact cell
D16: Impact \ Likelihood | E16: 1 | F16: 2 | G16: 3 | H16: 4 | I16: 5
D17: 5 | E17: =COUNTIFS($E$5:$E$12,E$16,$F$5:$F$12,$D17) -> 0 | F17: =COUNTIFS($E$5:$E$12,F$16,$F$5:$F$12,$D17) -> 0 | G17: =COUNTIFS($E$5:$E$12,G$16,$F$5:$F$12,$D17) -> 1 | H17: =COUNTIFS($E$5:$E$12,H$16,$F$5:$F$12,$D17) -> 2 | I17: =COUNTIFS($E$5:$E$12,I$16,$F$5:$F$12,$D17) -> 0
D18: 4 | E18: =COUNTIFS($E$5:$E$12,E$16,$F$5:$F$12,$D18) -> 0 | F18: =COUNTIFS($E$5:$E$12,F$16,$F$5:$F$12,$D18) -> 0 | G18: =COUNTIFS($E$5:$E$12,G$16,$F$5:$F$12,$D18) -> 0 | H18: =COUNTIFS($E$5:$E$12,H$16,$F$5:$F$12,$D18) -> 1 | I18: =COUNTIFS($E$5:$E$12,I$16,$F$5:$F$12,$D18) -> 0
D19: 3 | E19: =COUNTIFS($E$5:$E$12,E$16,$F$5:$F$12,$D19) -> 0 | F19: =COUNTIFS($E$5:$E$12,F$16,$F$5:$F$12,$D19) -> 0 | G19: =COUNTIFS($E$5:$E$12,G$16,$F$5:$F$12,$D19) -> 2 | H19: =COUNTIFS($E$5:$E$12,H$16,$F$5:$F$12,$D19) -> 1 | I19: =COUNTIFS($E$5:$E$12,I$16,$F$5:$F$12,$D19) -> 0
D20: 2 | E20: =COUNTIFS($E$5:$E$12,E$16,$F$5:$F$12,$D20) -> 0 | F20: =COUNTIFS($E$5:$E$12,F$16,$F$5:$F$12,$D20) -> 0 | G20: =COUNTIFS($E$5:$E$12,G$16,$F$5:$F$12,$D20) -> 0 | H20: =COUNTIFS($E$5:$E$12,H$16,$F$5:$F$12,$D20) -> 1 | I20: =COUNTIFS($E$5:$E$12,I$16,$F$5:$F$12,$D20) -> 0
D21: 1 | E21: =COUNTIFS($E$5:$E$12,E$16,$F$5:$F$12,$D21) -> 0 | F21: =COUNTIFS($E$5:$E$12,F$16,$F$5:$F$12,$D21) -> 0 | G21: =COUNTIFS($E$5:$E$12,G$16,$F$5:$F$12,$D21) -> 0 | H21: =COUNTIFS($E$5:$E$12,H$16,$F$5:$F$12,$D21) -> 0 | I21: =COUNTIFS($E$5:$E$12,I$16,$F$5:$F$12,$D21) -> 0

Sheet Mitigation
A1: Mitigation plan for the top three risks
A2: Actions are recommendations written from the evidence; owners are functions, not named people. Risk names pull from the Risks sheet. If you change the top three, update the action rows.
A4: Risk | B4: Risk name | C4: # | D4: Action | E4: Owner (function) | F4: Timing | G4: KPI / trigger | H4: Target
A5: R1 | B5: =INDEX(Risks!$B$5:$B$12,MATCH($A5,Risks!$A$5:$A$12,0)) -> Imported aluminium extrusion dependence | C5: 1 | D5: Stage-gate qualification of Hindalco Kuppam extrusion: sample lots, dimensional and surface capability studies, then volume release tied to measured yield, ahead of the March 2027 start. | E5: Sourcing + Supplier quality | F5: 0-9 months | G5: Qualified lots passed; domestic extrusion share of total | H5: Kuppam qualified before volume release
A6: R1 | B6: =INDEX(Risks!$B$5:$B$12,MATCH($A6,Risks!$A$5:$A$12,0)) -> Imported aluminium extrusion dependence | C6: 2 | D6: Hold safety stock and keep two approved import sources for extrusion until domestic yield is proven; set weeks of cover by lead time and lane risk. | E6: Supply chain planning | F6: 0-3 months | G6: Weeks of extrusion cover | H6: At least the longest-lane lead time plus buffer
A7: R1 | B7: =INDEX(Risks!$B$5:$B$12,MATCH($A7,Risks!$A$5:$A$12,0)) -> Imported aluminium extrusion dependence | C7: 3 | D7: Move extrusion pricing to an LME-linked index with a collar so metal price risk is shared and not buried in unit price. | E7: Sourcing (commodity team) | F7: 3-6 months | G7: Share of volume on index pricing | H7: All new extrusion contracts indexed
A8: R1 | B8: =INDEX(Risks!$B$5:$B$12,MATCH($A8,Risks!$A$5:$A$12,0)) -> Imported aluminium extrusion dependence | C8: 4 | D8: Pre-plan duty and customs treatment (bonded storage, duty-exemption eligibility) for imported extrusion and review quarterly against policy changes. | E8: Sourcing + Trade compliance | F8: 0-6 months | G8: Duty paid versus plan | H8: No unplanned duty cost
A9: R2 | B9: =INDEX(Risks!$B$5:$B$12,MATCH($A9,Risks!$A$5:$A$12,0)) -> Chinese equipment and engineer dependence | C9: 1 | D9: Run side-by-side capability studies of Indian machine and tooling makers (Titan Engineering, Jyoti CNC, Bharat Forge) against incumbent equipment on one pilot line. | E9: Engineering + Supplier development | F9: 0-9 months | G9: Pilot-line OEE and tolerance capability versus incumbent | H9: Within agreed gap of incumbent equipment
A10: R2 | B10: =INDEX(Risks!$B$5:$B$12,MATCH($A10,Risks!$A$5:$A$12,0)) -> Chinese equipment and engineer dependence | C10: 2 | D10: Dual-source critical equipment from non-China origins (for example Japan, Taiwan, Korea, Germany) and cut China's share of new equipment orders. | E10: Sourcing + Engineering | F10: 3-12 months | G10: Share of new equipment value from non-China origin | H10: Majority of new orders non-China
A11: R2 | B11: =INDEX(Risks!$B$5:$B$12,MATCH($A11,Risks!$A$5:$A$12,0)) -> Chinese equipment and engineer dependence | C11: 3 | D11: Build a skilling and tool-maintenance programme in India (train and certify local technicians and process engineers) so tool upkeep no longer depends on imported engineers. | E11: Supplier development + HR partners | F11: 0-12 months | G11: Certified Indian process engineers; mean time to repair | H11: Rising certified headcount; falling MTTR
A12: R2 | B12: =INDEX(Risks!$B$5:$B$12,MATCH($A12,Risks!$A$5:$A$12,0)) -> Chinese equipment and engineer dependence | C12: 4 | D12: Stock critical spares and consumable tooling in India with a defined buffer, and agree emergency supply terms with equipment makers. | E12: Supply chain planning | F12: 0-3 months | G12: Days of critical-spares cover | H12: Cover for longest equipment lead time
A13: R3 | B13: =INDEX(Risks!$B$5:$B$12,MATCH($A13,Risks!$A$5:$A$12,0)) -> Capacity ramp and execution delay | C13: 1 | D13: Release volume to each new plant (Kanchipuram sites, Hosur, Kuppam) only on milestone gates for capacity, yield and quality. | E13: Sourcing + Operations | F13: 0-12 months | G13: Gate passed on schedule | H13: No volume release without gate pass
A14: R3 | B14: =INDEX(Risks!$B$5:$B$12,MATCH($A14,Risks!$A$5:$A$12,0)) -> Capacity ramp and execution delay | C14: 2 | D14: Keep parallel supply across Tata, Yuzhan, Motherson and Aequs so one slip does not stop launch volume; cap any single plant's share. | E14: Sourcing (commodity team) | F14: 0-6 months | G14: Largest single-plant share of volume | H14: Capped at an agreed ceiling
A15: R3 | B15: =INDEX(Risks!$B$5:$B$12,MATCH($A15,Risks!$A$5:$A$12,0)) -> Capacity ramp and execution delay | C15: 3 | D15: Run a weekly ramp review (schedule, OEE, first-pass yield) with each supplier and escalate any slip beyond an agreed number of weeks. | E15: Operations + Supplier quality | F15: 0-12 months | G15: Schedule slip in weeks; first-pass yield versus plan | H15: Slip within tolerance; yield on plan
A16: R3 | B16: =INDEX(Risks!$B$5:$B$12,MATCH($A16,Risks!$A$5:$A$12,0)) -> Capacity ramp and execution delay | C16: 4 | D16: Keep contingency capacity at existing China or Vietnam enclosure lines during the first launch cycle of each new Indian line. | E16: Supply chain planning | F16: 0-12 months | G16: Contingency capacity available | H16: Enough to cover the largest ramping plant
A18: Residual risk after mitigation (from Risks sheet)
A19: Risk | B19: Risk name | D19: Score before | E19: Score after | F19: Reduction
A20: R1 | B20: =INDEX(Risks!$B$5:$B$12,MATCH($A20,Risks!$A$5:$A$12,0)) -> Imported aluminium extrusion dependence | D20: =INDEX(Risks!$G$5:$G$12,MATCH($A20,Risks!$A$5:$A$12,0)) -> 20 | E20: =INDEX(Risks!$M$5:$M$12,MATCH($A20,Risks!$A$5:$A$12,0)) -> 9 | F20: =1-E20/D20 -> 0.55
A21: R2 | B21: =INDEX(Risks!$B$5:$B$12,MATCH($A21,Risks!$A$5:$A$12,0)) -> Chinese equipment and engineer dependence | D21: =INDEX(Risks!$G$5:$G$12,MATCH($A21,Risks!$A$5:$A$12,0)) -> 20 | E21: =INDEX(Risks!$M$5:$M$12,MATCH($A21,Risks!$A$5:$A$12,0)) -> 12 | F21: =1-E21/D21 -> 0.4
A22: R3 | B22: =INDEX(Risks!$B$5:$B$12,MATCH($A22,Risks!$A$5:$A$12,0)) -> Capacity ramp and execution delay | D22: =INDEX(Risks!$G$5:$G$12,MATCH($A22,Risks!$A$5:$A$12,0)) -> 16 | E22: =INDEX(Risks!$M$5:$M$12,MATCH($A22,Risks!$A$5:$A$12,0)) -> 9 | F22: =1-E22/D22 -> 0.4375

Sheet Sources
A1: Sources (retrieved 22 Oct 2026)
A2: Press and trade reports; some rely on unnamed sources. Verify plant status before relying on any single item.
A4: Ref | B4: Report | C4: Used for | D4: URL
A5: 1 | B5: Digitimes, Mar 2025: Jabil, Aequs, Tata export Apple components to China and Vietnam | C5: Motherson, Jabil, Aequs, Tata producing enclosures; exports | D5: https://www.digitimes.com/news/a20250303VL205/apple-india-mobile-components-manufacturing-supplier.html
A6: 2 | B6: Digitimes, May 2025: Tata doubles Hosur iPhone enclosure production | C6: Tata output, Sept 2024 fire and restoration | D6: https://www.digitimes.com/news/a20250512VL204/iphone-apple-expansion-production-capacity.html
A7: 3 | B7: Business Standard, Nov 2025: Apple steps up India push as suppliers scale | C7: TD Connex expansion, Aequs trial production, Yuzhan | D7: https://www.business-standard.com/companies/news/apple-india-suppliers-manufacturing-expansion-investments-supply-chain-125111500797_1.html
A8: 4 | B8: EE Times India, Jan 2026: Government clears 22 more ECMS projects | C8: ECMS enclosure approvals; extrusion currently fully imported | D8: https://www.eetindia.co.in/government-clears-22-more-ecms-projects-deepening-indias-electronics-supply-chain/
A9: 5 | B9: Deccan Herald, 2025: Govt approves 17 ECMS projects (tranche 2) | C9: Aequs laptop and smartwatch enclosures; Jabil | D9: https://www.deccanherald.com/amp/story/india%2Fgovt-approves-17-projects-with-rs-7172-cr-investment-for-electronics-component-manufacturing-3801087
A10: 6 | B10: Ommcom News, 17 Aug 2026: Govt clears 31 ECMS projects | C10: 106 approvals, ₹69,548 crore; Hosur, Kanchipuram enclosure plants | D10: https://ommcomnews.com/india-news/govt-clears-31-ecms-projects-worth-rs-7877-crore-106-approvals-now-total-rs-69548-crore/
A11: 7 | B11: Steel News (Yieh), Sep 2025: Hindalco extrusion plant in Andhra Pradesh | C11: ₹586 crore Kuppam plant, March 2027 | D11: https://www.yieh.com/en/News/hindalco-to-build-aluminum-extrusion-plant-in-andhra-pradesh-for-iphones-chassis/156598
A12: 8 | B12: Global SMT: India makes one in four iPhones; the aluminium body is still imported | C12: 100% imported extrusion; Hindalco capacity | D12: https://www.globalsmt.net/?p=105209
A13: 9 | B13: The420: Apple forms anchor vendor team under ECMS | C13: Tata supplies a limited share of enclosures | D13: https://the420.in/?p=61627
A14: 10 | B14: Rest of World: Foxconn stops sending Chinese workers to India | C14: Held-up equipment; India lacked some technology | D14: https://restofworld.org/2025/china-foxconn-factoriesfoxconn-stops-sending-chinese-workers-to-india-iphone-factories/
A15: 11 | B15: Deccan Herald / Bloomberg: Foxconn recall of Chinese staff | C15: About 300 engineers recalled; Yuzhan makes older-iPhone enclosures | D15: https://www.deccanherald.com/amp/story/business%2Ffoxconns-recall-of-more-chinese-staff-tests-apples-india-push-3694305
A16: 12 | B16: NewsBytes, Sep 2025: Apple strengthens India manufacturing with machinery | C16: About 35 machinery makers; TEAL, Jyoti CNC, Bharat Forge, Wipro | D16: https://www.newsbytesapp.com/news/business/apple-boosts-iphone-production-in-india-amid-china-tensions/story
... A29: 26 | B29: J2T: Aluminium price forecast 2026-2030 | C29: Analyst range for 2026 average price | D29: https://j2t.com/solutions/blogview/aluminium-price-forecast/
